uart_project/rtl/baud_generator.v
`timescale 1ns/1ps


module baud_generator
#(
    parameter CLKS_PER_BIT = 217
)
(
    input wire clk,
    input wire rst_n,

    output reg baud_tick
);

reg [7:0] counter;

always @(posedge clk)
begin
    if(!rst_n)
    begin
        counter   <= 8'd0;
        baud_tick <= 1'b0;
    end

    else
    begin
        if(counter == CLKS_PER_BIT-1)
        begin
            counter   <= 8'd0;
            baud_tick <= 1'b1;
        end

        else
        begin
            counter   <= counter + 1'b1;
            baud_tick <= 1'b0;
        end
    end
end

endmodule

uart_project/tb/baud_generator_tb.v
`timescale 1ns/1ps

module baud_generator_tb;

reg clk;
reg rst_n;

wire baud_tick;

baud_generator uut
(
    .clk(clk),
    .rst_n(rst_n),
    .baud_tick(baud_tick)
);

// 25 MHz Clock
always #20 clk <= ~clk;

initial
begin
    clk   = 0;
    rst_n = 0;

    #100;

    rst_n = 1;

    #20000;

    $finish;
end

always @(posedge clk)
begin
    if(baud_tick)
        $display("Time=%0t ns | Baud Tick Generated", $time);
end

initial
begin
    $dumpfile("baud_generator.vcd");
    $dumpvars(0, baud_generator_tb);
end

endmodule

uart_project/results/baud_generator.vcd
$version Generated by VerilatedVcd $end
$timescale 1ps $end
 $scope module TOP $end
  $scope module baud_generator_tb $end
   $var wire 1 # clk $end
   $var wire 1 $ rst_n $end
   $var wire 1 % baud_tick $end
   $scope module uut $end
    $var wire 32 ' CLKS_PER_BIT [31:0] $end
    $var wire 1 # clk $end
    $var wire 1 $ rst_n $end
    $var wire 1 % baud_tick $end
    $var wire 8 & counter [7:0] $end
   $upscope $end
  $upscope $end
 $upscope $end
$enddefinitions $end


#0
0#
0$
0%
b00000000 &
b00000000000000000000000011011001 '
#20000
1#
#40000
0#
#60000
1#
#80000
0#
#100000
1#
1$
b00000001 &
#120000
0#
#140000
1#
b00000010 &
#160000
0#
#180000
1#
b00000011 &
#200000
0#
#220000
1#
b00000100 &
#240000
0#
#260000
1#
b00000101 &
#280000
0#
#300000
1#
b00000110 &
#320000
0#
#340000
1#
b00000111 &
#360000
0#
#380000
1#
b00001000 &
#400000
0#
#420000
1#
b00001001 &
#440000
0#
#460000
1#
b00001010 &
#480000
0#
#500000
1#
b00001011 &
#520000
0#
#540000
1#
b00001100 &
#560000
0#
#580000
1#
b00001101 &
#600000
0#
#620000
1#
b00001110 &
#640000
0#
#660000
1#
b00001111 &
#680000
0#
#700000
1#
b00010000 &
#720000
0#
#740000
1#
b00010001 &
#760000
0#
#780000
1#
b00010010 &
#800000
0#
#820000
1#
b00010011 &
#840000
0#
#860000
1#
b00010100 &
#880000
0#
#900000
1#
b00010101 &
#920000
0#
#940000
1#
b00010110 &
#960000
0#
#980000
1#
b00010111 &
#1000000
0#
#1020000
1#
b00011000 &
#1040000
0#
#1060000
1#
b00011001 &
#1080000
0#
#1100000
1#
b00011010 &
#1120000
0#
#1140000
1#
b00011011 &
#1160000
0#
#1180000
1#
b00011100 &
#1200000
0#
#1220000
1#
b00011101 &
#1240000
0#
#1260000
1#
b00011110 &
#1280000
0#
#1300000
1#
b00011111 &
#1320000
0#
#1340000
1#
b00100000 &
#1360000
0#
#1380000
1#
b00100001 &
#1400000
0#
#1420000
1#
b00100010 &
#1440000
0#
#1460000
1#
b00100011 &
#1480000
0#
#1500000
1#
b00100100 &
#1520000
0#
#1540000
1#
b00100101 &
#1560000
0#
#1580000
1#
b00100110 &
#1600000
0#
#1620000
1#
b00100111 &
#1640000
0#
#1660000
1#
b00101000 &
#1680000
0#
#1700000
1#
b00101001 &
#1720000
0#
#1740000
1#
b00101010 &
#1760000
0#
#1780000
1#
b00101011 &
#1800000
0#
#1820000
1#
b00101100 &
#1840000
0#
#1860000
1#
b00101101 &
#1880000
0#
#1900000
1#
b00101110 &
#1920000
0#
#1940000
1#
b00101111 &
#1960000
0#
#1980000
1#
b00110000 &
#2000000
0#
#2020000
1#
b00110001 &
#2040000
0#
#2060000
1#
b00110010 &
#2080000
0#
#2100000
1#
b00110011 &
#2120000
0#
#2140000
1#
b00110100 &
#2160000
0#
#2180000
1#
b00110101 &
#2200000
0#
#2220000
1#
b00110110 &
#2240000
0#
#2260000
1#
b00110111 &
#2280000
0#
#2300000
1#
b00111000 &
#2320000
0#
#2340000
1#
b00111001 &
#2360000
0#
#2380000
1#
b00111010 &
#2400000
0#
#2420000
1#
b00111011 &
#2440000
0#
#2460000
1#
b00111100 &
#2480000
0#
#2500000
1#
b00111101 &
#2520000
0#
#2540000
1#
b00111110 &
#2560000
0#
#2580000
1#
b00111111 &
#2600000
0#
#2620000
1#
b01000000 &
#2640000
0#
#2660000
1#
b01000001 &
#2680000
0#
#2700000
1#
b01000010 &
#2720000
0#
#2740000
1#
b01000011 &
#2760000
0#
#2780000
1#
b01000100 &
#2800000
0#
#2820000
1#
b01000101 &
#2840000
0#
#2860000
1#
b01000110 &
#2880000
0#
#2900000
1#
b01000111 &
#2920000
0#
#2940000
1#
b01001000 &
#2960000
0#
#2980000
1#
b01001001 &
#3000000
0#
#3020000
1#
b01001010 &
#3040000
0#
#3060000
1#
b01001011 &
#3080000
0#
#3100000
1#
b01001100 &
#3120000
0#
#3140000
1#
b01001101 &
#3160000
0#
#3180000
1#
b01001110 &
#3200000
0#
#3220000
1#
b01001111 &
#3240000
0#
#3260000
1#
b01010000 &
#3280000
0#
#3300000
1#
b01010001 &
#3320000
0#
#3340000
1#
b01010010 &
#3360000
0#
#3380000
1#
b01010011 &
#3400000
0#
#3420000
1#
b01010100 &
#3440000
0#
#3460000
1#
b01010101 &
#3480000
0#
#3500000
1#
b01010110 &
#3520000
0#
#3540000
1#
b01010111 &
#3560000
0#
#3580000
1#
b01011000 &
#3600000
0#
#3620000
1#
b01011001 &
#3640000
0#
#3660000
1#
b01011010 &
#3680000
0#
#3700000
1#
b01011011 &
#3720000
0#
#3740000
1#
b01011100 &
#3760000
0#
#3780000
1#
b01011101 &
#3800000
0#
#3820000
1#
b01011110 &
#3840000
0#
#3860000
1#
b01011111 &
#3880000
0#
#3900000
1#
b01100000 &
#3920000
0#
#3940000
1#
b01100001 &
#3960000
0#
#3980000
1#
b01100010 &
#4000000
0#
#4020000
1#
b01100011 &
#4040000
0#
#4060000
1#
b01100100 &
#4080000
0#
#4100000
1#
b01100101 &
#4120000
0#
#4140000
1#
b01100110 &
#4160000
0#
#4180000
1#
b01100111 &
#4200000
0#
#4220000
1#
b01101000 &
#4240000
0#
#4260000
1#
b01101001 &
#4280000
0#
#4300000
1#
b01101010 &
#4320000
0#
#4340000
1#
b01101011 &
#4360000
0#
#4380000
1#
b01101100 &
#4400000
0#
#4420000
1#
b01101101 &
#4440000
0#
#4460000
1#
b01101110 &
#4480000
0#
#4500000
1#
b01101111 &
#4520000
0#
#4540000
1#
b01110000 &
#4560000
0#
#4580000
1#
b01110001 &
#4600000
0#
#4620000
1#
b01110010 &
#4640000
0#
#4660000
1#
b01110011 &
#4680000
0#
#4700000
1#
b01110100 &
#4720000
0#
#4740000
1#
b01110101 &
#4760000
0#
#4780000
1#
b01110110 &
#4800000
0#
#4820000
1#
b01110111 &
#4840000
0#
#4860000
1#
b01111000 &
#4880000
0#
#4900000
1#
b01111001 &
#4920000
0#
#4940000
1#
b01111010 &
#4960000
0#
#4980000
1#
b01111011 &
#5000000
0#
#5020000
1#
b01111100 &
#5040000
0#
#5060000
1#
b01111101 &
#5080000
0#
#5100000
1#
b01111110 &
#5120000
0#
#5140000
1#
b01111111 &
#5160000
0#
#5180000
1#
b10000000 &
#5200000
0#
#5220000
1#
b10000001 &
#5240000
0#
#5260000
1#
b10000010 &
#5280000
0#
#5300000
1#
b10000011 &
#5320000
0#
#5340000
1#
b10000100 &
#5360000
0#
#5380000
1#
b10000101 &
#5400000
0#
#5420000
1#
b10000110 &
#5440000
0#
#5460000
1#
b10000111 &
#5480000
0#
#5500000
1#
b10001000 &
#5520000
0#
#5540000
1#
b10001001 &
#5560000
0#
#5580000
1#
b10001010 &
#5600000
0#
#5620000
1#
b10001011 &
#5640000
0#
#5660000
1#
b10001100 &
#5680000
0#
#5700000
1#
b10001101 &
#5720000
0#
#5740000
1#
b10001110 &
#5760000
0#
#5780000
1#
b10001111 &
#5800000
0#
#5820000
1#
b10010000 &
#5840000
0#
#5860000
1#
b10010001 &
#5880000
0#
#5900000
1#
b10010010 &
#5920000
0#
#5940000
1#
b10010011 &
#5960000
0#
#5980000
1#
b10010100 &
#6000000
0#
#6020000
1#
b10010101 &
#6040000
0#
#6060000
1#
b10010110 &
#6080000
0#
#6100000
1#
b10010111 &
#6120000
0#
#6140000
1#
b10011000 &
#6160000
0#
#6180000
1#
b10011001 &
#6200000
0#
#6220000
1#
b10011010 &
#6240000
0#
#6260000
1#
b10011011 &
#6280000
0#
#6300000
1#
b10011100 &
#6320000
0#
#6340000
1#
b10011101 &
#6360000
0#
#6380000
1#
b10011110 &
#6400000
0#
#6420000
1#
b10011111 &
#6440000
0#
#6460000
1#
b10100000 &
#6480000
0#
#6500000
1#
b10100001 &
#6520000
0#
#6540000
1#
b10100010 &
#6560000
0#
#6580000
1#
b10100011 &
#6600000
0#
#6620000
1#
b10100100 &
#6640000
0#
#6660000
1#
b10100101 &
#6680000
0#
#6700000
1#
b10100110 &
#6720000
0#
#6740000
1#
b10100111 &
#6760000
0#
#6780000
1#
b10101000 &
#6800000
0#
#6820000
1#
b10101001 &
#6840000
0#
#6860000
1#
b10101010 &
#6880000
0#
#6900000
1#
b10101011 &
#6920000
0#
#6940000
1#
b10101100 &
#6960000
0#
#6980000
1#
b10101101 &
#7000000
0#
#7020000
1#
b10101110 &
#7040000
0#
#7060000
1#
b10101111 &
#7080000
0#
#7100000
1#
b10110000 &
#7120000
0#
#7140000
1#
b10110001 &
#7160000
0#
#7180000
1#
b10110010 &
#7200000
0#
#7220000
1#
b10110011 &
#7240000
0#
#7260000
1#
b10110100 &
#7280000
0#
#7300000
1#
b10110101 &
#7320000
0#
#7340000
1#
b10110110 &
#7360000
0#
#7380000
1#
b10110111 &
#7400000
0#
#7420000
1#
b10111000 &
#7440000
0#
#7460000
1#
b10111001 &
#7480000
0#
#7500000
1#
b10111010 &
#7520000
0#
#7540000
1#
b10111011 &
#7560000
0#
#7580000
1#
b10111100 &
#7600000
0#
#7620000
1#
b10111101 &
#7640000
0#
#7660000
1#
b10111110 &
#7680000
0#
#7700000
1#
b10111111 &
#7720000
0#
#7740000
1#
b11000000 &
#7760000
0#
#7780000
1#
b11000001 &
#7800000
0#
#7820000
1#
b11000010 &
#7840000
0#
#7860000
1#
b11000011 &
#7880000
0#
#7900000
1#
b11000100 &
#7920000
0#
#7940000
1#
b11000101 &
#7960000
0#
#7980000
1#
b11000110 &
#8000000
0#
#8020000
1#
b11000111 &
#8040000
0#
#8060000
1#
b11001000 &
#8080000
0#
#8100000
1#
b11001001 &
#8120000
0#
#8140000
1#
b11001010 &
#8160000
0#
#8180000
1#
b11001011 &
#8200000
0#
#8220000
1#
b11001100 &
#8240000
0#
#8260000
1#
b11001101 &
#8280000
0#
#8300000
1#
b11001110 &
#8320000
0#
#8340000
1#
b11001111 &
#8360000
0#
#8380000
1#
b11010000 &
#8400000
0#
#8420000
1#
b11010001 &
#8440000
0#
#8460000
1#
b11010010 &
#8480000
0#
#8500000
1#
b11010011 &
#8520000
0#
#8540000
1#
b11010100 &
#8560000
0#
#8580000
1#
b11010101 &
#8600000
0#
#8620000
1#
b11010110 &
#8640000
0#
#8660000
1#
b11010111 &
#8680000
0#
#8700000
1#
b11011000 &
#8720000
0#
#8740000
1#
1%
b00000000 &
#8760000
0#
#8780000
1#
0%
b00000001 &
#8800000
0#
#8820000
1#
b00000010 &
#8840000
0#
#8860000
1#
b00000011 &
#8880000
0#
#8900000
1#
b00000100 &
#8920000
0#
#8940000
1#
b00000101 &
#8960000
0#
#8980000
1#
b00000110 &
#9000000
0#
#9020000
1#
b00000111 &
#9040000
0#
#9060000
1#
b00001000 &
#9080000
0#
#9100000
1#
b00001001 &
#9120000
0#
#9140000
1#
b00001010 &
#9160000
0#
#9180000
1#
b00001011 &
#9200000
0#
#9220000
1#
b00001100 &
#9240000
0#
#9260000
1#
b00001101 &
#9280000
0#
#9300000
1#
b00001110 &
#9320000
0#
#9340000
1#
b00001111 &
#9360000
0#
#9380000
1#
b00010000 &
#9400000
0#
#9420000
1#
b00010001 &
#9440000
0#
#9460000
1#
b00010010 &
#9480000
0#
#9500000
1#
b00010011 &
#9520000
0#
#9540000
1#
b00010100 &
#9560000
0#
#9580000
1#
b00010101 &
#9600000
0#
#9620000
1#
b00010110 &
#9640000
0#
#9660000
1#
b00010111 &
#9680000
0#
#9700000
1#
b00011000 &
#9720000
0#
#9740000
1#
b00011001 &
#9760000
0#
#9780000
1#
b00011010 &
#9800000
0#
#9820000
1#
b00011011 &
#9840000
0#
#9860000
1#
b00011100 &
#9880000
0#
#9900000
1#
b00011101 &
#9920000
0#
#9940000
1#
b00011110 &
#9960000
0#
#9980000
1#
b00011111 &
#10000000
0#
#10020000
1#
b00100000 &
#10040000
0#
#10060000
1#
b00100001 &
#10080000
0#
#10100000
1#
b00100010 &
#10120000
0#
#10140000
1#
b00100011 &
#10160000
0#
#10180000
1#
b00100100 &
#10200000
0#
#10220000
1#
b00100101 &
#10240000
0#
#10260000
1#
b00100110 &
#10280000
0#
#10300000
1#
b00100111 &
#10320000
0#
#10340000
1#
b00101000 &
#10360000
0#
#10380000
1#
b00101001 &
#10400000
0#
#10420000
1#
b00101010 &
#10440000
0#
#10460000
1#
b00101011 &
#10480000
0#
#10500000
1#
b00101100 &
#10520000
0#
#10540000
1#
b00101101 &
#10560000
0#
#10580000
1#
b00101110 &
#10600000
0#
#10620000
1#
b00101111 &
#10640000
0#
#10660000
1#
b00110000 &
#10680000
0#
#10700000
1#
b00110001 &
#10720000
0#
#10740000
1#
b00110010 &
#10760000
0#
#10780000
1#
b00110011 &
#10800000
0#
#10820000
1#
b00110100 &
#10840000
0#
#10860000
1#
b00110101 &
#10880000
0#
#10900000
1#
b00110110 &
#10920000
0#
#10940000
1#
b00110111 &
#10960000
0#
#10980000
1#
b00111000 &
#11000000
0#
#11020000
1#
b00111001 &
#11040000
0#
#11060000
1#
b00111010 &
#11080000
0#
#11100000
1#
b00111011 &
#11120000
0#
#11140000
1#
b00111100 &
#11160000
0#
#11180000
1#
b00111101 &
#11200000
0#
#11220000
1#
b00111110 &
#11240000
0#
#11260000
1#
b00111111 &
#11280000
0#
#11300000
1#
b01000000 &
#11320000
0#
#11340000
1#
b01000001 &
#11360000
0#
#11380000
1#
b01000010 &
#11400000
0#
#11420000
1#
b01000011 &
#11440000
0#
#11460000
1#
b01000100 &
#11480000
0#
#11500000
1#
b01000101 &
#11520000
0#
#11540000
1#
b01000110 &
#11560000
0#
#11580000
1#
b01000111 &
#11600000
0#
#11620000
1#
b01001000 &
#11640000
0#
#11660000
1#
b01001001 &
#11680000
0#
#11700000
1#
b01001010 &
#11720000
0#
#11740000
1#
b01001011 &
#11760000
0#
#11780000
1#
b01001100 &
#11800000
0#
#11820000
1#
b01001101 &
#11840000
0#
#11860000
1#
b01001110 &
#11880000
0#
#11900000
1#
b01001111 &
#11920000
0#
#11940000
1#
b01010000 &
#11960000
0#
#11980000
1#
b01010001 &
#12000000
0#
#12020000
1#
b01010010 &
#12040000
0#
#12060000
1#
b01010011 &
#12080000
0#
#12100000
1#
b01010100 &
#12120000
0#
#12140000
1#
b01010101 &
#12160000
0#
#12180000
1#
b01010110 &
#12200000
0#
#12220000
1#
b01010111 &
#12240000
0#
#12260000
1#
b01011000 &
#12280000
0#
#12300000
1#
b01011001 &
#12320000
0#
#12340000
1#
b01011010 &
#12360000
0#
#12380000
1#
b01011011 &
#12400000
0#
#12420000
1#
b01011100 &
#12440000
0#
#12460000
1#
b01011101 &
#12480000
0#
#12500000
1#
b01011110 &
#12520000
0#
#12540000
1#
b01011111 &
#12560000
0#
#12580000
1#
b01100000 &
#12600000
0#
#12620000
1#
b01100001 &
#12640000
0#
#12660000
1#
b01100010 &
#12680000
0#
#12700000
1#
b01100011 &
#12720000
0#
#12740000
1#
b01100100 &
#12760000
0#
#12780000
1#
b01100101 &
#12800000
0#
#12820000
1#
b01100110 &
#12840000
0#
#12860000
1#
b01100111 &
#12880000
0#
#12900000
1#
b01101000 &
#12920000
0#
#12940000
1#
b01101001 &
#12960000
0#
#12980000
1#
b01101010 &
#13000000
0#
#13020000
1#
b01101011 &
#13040000
0#
#13060000
1#
b01101100 &
#13080000
0#
#13100000
1#
b01101101 &
#13120000
0#
#13140000
1#
b01101110 &
#13160000
0#
#13180000
1#
b01101111 &
#13200000
0#
#13220000
1#
b01110000 &
#13240000
0#
#13260000
1#
b01110001 &
#13280000
0#
#13300000
1#
b01110010 &
#13320000
0#
#13340000
1#
b01110011 &
#13360000
0#
#13380000
1#
b01110100 &
#13400000
0#
#13420000
1#
b01110101 &
#13440000
0#
#13460000
1#
b01110110 &
#13480000
0#
#13500000
1#
b01110111 &
#13520000
0#
#13540000
1#
b01111000 &
#13560000
0#
#13580000
1#
b01111001 &
#13600000
0#
#13620000
1#
b01111010 &
#13640000
0#
#13660000
1#
b01111011 &
#13680000
0#
#13700000
1#
b01111100 &
#13720000
0#
#13740000
1#
b01111101 &
#13760000
0#
#13780000
1#
b01111110 &
#13800000
0#
#13820000
1#
b01111111 &
#13840000
0#
#13860000
1#
b10000000 &
#13880000
0#
#13900000
1#
b10000001 &
#13920000
0#
#13940000
1#
b10000010 &
#13960000
0#
#13980000
1#
b10000011 &
#14000000
0#
#14020000
1#
b10000100 &
#14040000
0#
#14060000
1#
b10000101 &
#14080000
0#
#14100000
1#
b10000110 &
#14120000
0#
#14140000
1#
b10000111 &
#14160000
0#
#14180000
1#
b10001000 &
#14200000
0#
#14220000
1#
b10001001 &
#14240000
0#
#14260000
1#
b10001010 &
#14280000
0#
#14300000
1#
b10001011 &
#14320000
0#
#14340000
1#
b10001100 &
#14360000
0#
#14380000
1#
b10001101 &
#14400000
0#
#14420000
1#
b10001110 &
#14440000
0#
#14460000
1#
b10001111 &
#14480000
0#
#14500000
1#
b10010000 &
#14520000
0#
#14540000
1#
b10010001 &
#14560000
0#
#14580000
1#
b10010010 &
#14600000
0#
#14620000
1#
b10010011 &
#14640000
0#
#14660000
1#
b10010100 &
#14680000
0#
#14700000
1#
b10010101 &
#14720000
0#
#14740000
1#
b10010110 &
#14760000
0#
#14780000
1#
b10010111 &
#14800000
0#
#14820000
1#
b10011000 &
#14840000
0#
#14860000
1#
b10011001 &
#14880000
0#
#14900000
1#
b10011010 &
#14920000
0#
#14940000
1#
b10011011 &
#14960000
0#
#14980000
1#
b10011100 &
#15000000
0#
#15020000
1#
b10011101 &
#15040000
0#
#15060000
1#
b10011110 &
#15080000
0#
#15100000
1#
b10011111 &
#15120000
0#
#15140000
1#
b10100000 &
#15160000
0#
#15180000
1#
b10100001 &
#15200000
0#
#15220000
1#
b10100010 &
#15240000
0#
#15260000
1#
b10100011 &
#15280000
0#
#15300000
1#
b10100100 &
#15320000
0#
#15340000
1#
b10100101 &
#15360000
0#
#15380000
1#
b10100110 &
#15400000
0#
#15420000
1#
b10100111 &
#15440000
0#
#15460000
1#
b10101000 &
#15480000
0#
#15500000
1#
b10101001 &
#15520000
0#
#15540000
1#
b10101010 &
#15560000
0#
#15580000
1#
b10101011 &
#15600000
0#
#15620000
1#
b10101100 &
#15640000
0#
#15660000
1#
b10101101 &
#15680000
0#
#15700000
1#
b10101110 &
#15720000
0#
#15740000
1#
b10101111 &
#15760000
0#
#15780000
1#
b10110000 &
#15800000
0#
#15820000
1#
b10110001 &
#15840000
0#
#15860000
1#
b10110010 &
#15880000
0#
#15900000
1#
b10110011 &
#15920000
0#
#15940000
1#
b10110100 &
#15960000
0#
#15980000
1#
b10110101 &
#16000000
0#
#16020000
1#
b10110110 &
#16040000
0#
#16060000
1#
b10110111 &
#16080000
0#
#16100000
1#
b10111000 &
#16120000
0#
#16140000
1#
b10111001 &
#16160000
0#
#16180000
1#
b10111010 &
#16200000
0#
#16220000
1#
b10111011 &
#16240000
0#
#16260000
1#
b10111100 &
#16280000
0#
#16300000
1#
b10111101 &
#16320000
0#
#16340000
1#
b10111110 &
#16360000
0#
#16380000
1#
b10111111 &
#16400000
0#
#16420000
1#
b11000000 &
#16440000
0#
#16460000
1#
b11000001 &
#16480000
0#
#16500000
1#
b11000010 &
#16520000
0#
#16540000
1#
b11000011 &
#16560000
0#
#16580000
1#
b11000100 &
#16600000
0#
#16620000
1#
b11000101 &
#16640000
0#
#16660000
1#
b11000110 &
#16680000
0#
#16700000
1#
b11000111 &
#16720000
0#
#16740000
1#
b11001000 &
#16760000
0#
#16780000
1#
b11001001 &
#16800000
0#
#16820000
1#
b11001010 &
#16840000
0#
#16860000
1#
b11001011 &
#16880000
0#
#16900000
1#
b11001100 &
#16920000
0#
#16940000
1#
b11001101 &
#16960000
0#
#16980000
1#
b11001110 &
#17000000
0#
#17020000
1#
b11001111 &
#17040000
0#
#17060000
1#
b11010000 &
#17080000
0#
#17100000
1#
b11010001 &
#17120000
0#
#17140000
1#
b11010010 &
#17160000
0#
#17180000
1#
b11010011 &
#17200000
0#
#17220000
1#
b11010100 &
#17240000
0#
#17260000
1#
b11010101 &
#17280000
0#
#17300000
1#
b11010110 &
#17320000
0#
#17340000
1#
b11010111 &
#17360000
0#
#17380000
1#
b11011000 &
#17400000
0#
#17420000
1#
1%
b00000000 &
#17440000
0#
#17460000
1#
0%
b00000001 &
#17480000
0#
#17500000
1#
b00000010 &
#17520000
0#
#17540000
1#
b00000011 &
#17560000
0#
#17580000
1#
b00000100 &
#17600000
0#
#17620000
1#
b00000101 &
#17640000
0#
#17660000
1#
b00000110 &
#17680000
0#
#17700000
1#
b00000111 &
#17720000
0#
#17740000
1#
b00001000 &
#17760000
0#
#17780000
1#
b00001001 &
#17800000
0#
#17820000
1#
b00001010 &
#17840000
0#
#17860000
1#
b00001011 &
#17880000
0#
#17900000
1#
b00001100 &
#17920000
0#
#17940000
1#
b00001101 &
#17960000
0#
#17980000
1#
b00001110 &
#18000000
0#
#18020000
1#
b00001111 &
#18040000
0#
#18060000
1#
b00010000 &
#18080000
0#
#18100000
1#
b00010001 &
#18120000
0#
#18140000
1#
b00010010 &
#18160000
0#
#18180000
1#
b00010011 &
#18200000
0#
#18220000
1#
b00010100 &
#18240000
0#
#18260000
1#
b00010101 &
#18280000
0#
#18300000
1#
b00010110 &
#18320000
0#
#18340000
1#
b00010111 &
#18360000
0#
#18380000
1#
b00011000 &
#18400000
0#
#18420000
1#
b00011001 &
#18440000
0#
#18460000
1#
b00011010 &
#18480000
0#
#18500000
1#
b00011011 &
#18520000
0#
#18540000
1#
b00011100 &
#18560000
0#
#18580000
1#
b00011101 &
#18600000
0#
#18620000
1#
b00011110 &
#18640000
0#
#18660000
1#
b00011111 &
#18680000
0#
#18700000
1#
b00100000 &
#18720000
0#
#18740000
1#
b00100001 &
#18760000
0#
#18780000
1#
b00100010 &
#18800000
0#
#18820000
1#
b00100011 &
#18840000
0#
#18860000
1#
b00100100 &
#18880000
0#
#18900000
1#
b00100101 &
#18920000
0#
#18940000
1#
b00100110 &
#18960000
0#
#18980000
1#
b00100111 &
#19000000
0#
#19020000
1#
b00101000 &
#19040000
0#
#19060000
1#
b00101001 &
#19080000
0#
#19100000
1#
b00101010 &
#19120000
0#
#19140000
1#
b00101011 &
#19160000
0#
#19180000
1#
b00101100 &
#19200000
0#
#19220000
1#
b00101101 &
#19240000
0#
#19260000
1#
b00101110 &
#19280000
0#
#19300000
1#
b00101111 &
#19320000
0#
#19340000
1#
b00110000 &
#19360000
0#
#19380000
1#
b00110001 &
#19400000
0#
#19420000
1#
b00110010 &
#19440000
0#
#19460000
1#
b00110011 &
#19480000
0#
#19500000
1#
b00110100 &
#19520000
0#
#19540000
1#
b00110101 &
#19560000
0#
#19580000
1#
b00110110 &
#19600000
0#
#19620000
1#
b00110111 &
#19640000
0#
#19660000
1#
b00111000 &
#19680000
0#
#19700000
1#
b00111001 &
#19720000
0#
#19740000
1#
b00111010 &
#19760000
0#
#19780000
1#
b00111011 &
#19800000
0#
#19820000
1#
b00111100 &
#19840000
0#
#19860000
1#
b00111101 &
#19880000
0#
#19900000
1#
b00111110 &
#19920000
0#
#19940000
1#
b00111111 &
#19960000
0#
#19980000
1#
b01000000 &
#20000000
0#
#20020000
1#
b01000001 &
#20040000
0#
#20060000
1#
b01000010 &
#20080000
0#
#20100000
1#
b01000011 &
