uart_project/rtl/uart_tx.v
`timescale 1ns/1ps

module uart_tx
#(
    parameter CLKS_PER_BIT = 217
)
(
    input  wire       clk,
    input  wire       rst_n,
    input  wire       tx_start,
    input  wire [7:0] tx_data,

    output reg        tx,
    output reg        tx_busy
);

localparam IDLE  = 2'd0;
localparam START = 2'd1;
localparam DATA  = 2'd2;
localparam STOP  = 2'd3;

reg [1:0] state;
reg [7:0] clk_count;
reg [2:0] bit_index;
reg [7:0] data_buf;

always @(posedge clk)
begin
    if(!rst_n)
    begin
        state      <= IDLE;
        tx         <= 1'b1;
        tx_busy    <= 1'b0;
        clk_count  <= 8'd0;
        bit_index  <= 3'd0;
        data_buf   <= 8'd0;
    end
    else
    begin

        case(state)

        //--------------------------------
        IDLE:
        //--------------------------------
        begin
            tx <= 1'b1;
            tx_busy <= 1'b0;

            if(tx_start)
            begin
                data_buf <= tx_data;
                state <= START;
                tx_busy <= 1'b1;
            end
        end

        //--------------------------------
        START:
        //--------------------------------
        begin
            tx <= 1'b0;

            if(clk_count == CLKS_PER_BIT-1)
            begin
                clk_count <= 0;
                state <= DATA;
            end
            else
                clk_count <= clk_count + 1;
        end

        //--------------------------------
        DATA:
        //--------------------------------
        begin
            tx <= data_buf[bit_index];

            if(clk_count == CLKS_PER_BIT-1)
            begin
                clk_count <= 0;

                if(bit_index == 7)
                begin
                    bit_index <= 0;
                    state <= STOP;
                end
                else
                    bit_index <= bit_index + 1;
            end
            else
                clk_count <= clk_count + 1;
        end

        //--------------------------------
        STOP:
        //--------------------------------
        begin
            tx <= 1'b1;

            if(clk_count == CLKS_PER_BIT-1)
            begin
                clk_count <= 0;
                tx_busy <= 1'b0;
                state <= IDLE;
            end
            else
                clk_count <= clk_count + 1;
        end

        default:
            state <= IDLE;

        endcase
    end
end

endmodule

uart_project/tb/uart_tx_tb.v
`timescale 1ns/1ps

module uart_tx_tb;

localparam CLKS_PER_BIT = 217;

reg clk;
reg rst_n;
reg tx_start;
reg [7:0] tx_data;

wire tx;
wire tx_busy;

uart_tx #(
    .CLKS_PER_BIT(CLKS_PER_BIT)
)
dut
(
    .clk(clk),
    .rst_n(rst_n),
    .tx_start(tx_start),
    .tx_data(tx_data),
    .tx(tx),
    .tx_busy(tx_busy)
);

// 25 MHz clock
always #20 clk <= ~clk;

initial
begin
    clk      = 0;
    rst_n    = 0;
    tx_start = 0;
    tx_data  = 8'h00;

    #100;

    rst_n = 1;

    #100;

    // Send 0x3C
    tx_data  = 8'h3C;
    tx_start = 1;

    #40;
    tx_start = 0;

    wait(tx_busy == 0);

    #5000;

    $finish;
end

initial
begin
    $dumpfile("uart_tx.vcd");
    $dumpvars(0, uart_tx_tb);
end

always @(posedge clk)
begin
    if(tx_busy)
        $display("Time=%0t TX=%b", $time, tx);
end

endmodule

uart_project/results/uart_tx.vcd
$version Generated by VerilatedVcd $end
$timescale 1ps $end
 $scope module TOP $end
  $scope module uart_tx_tb $end
   $var wire 32 - CLKS_PER_BIT [31:0] $end
   $var wire 1 ) clk $end
   $var wire 1 * rst_n $end
   $var wire 1 + tx_start $end
   $var wire 8 , tx_data [7:0] $end
   $var wire 1 # tx $end
   $var wire 1 $ tx_busy $end
   $scope module dut $end
    $var wire 32 - CLKS_PER_BIT [31:0] $end
    $var wire 1 ) clk $end
    $var wire 1 * rst_n $end
    $var wire 1 + tx_start $end
    $var wire 8 , tx_data [7:0] $end
    $var wire 1 # tx $end
    $var wire 1 $ tx_busy $end
    $var wire 2 . IDLE [1:0] $end
    $var wire 2 / START [1:0] $end
    $var wire 2 0 DATA [1:0] $end
    $var wire 2 1 STOP [1:0] $end
    $var wire 2 % state [1:0] $end
    $var wire 8 & clk_count [7:0] $end
    $var wire 3 ' bit_index [2:0] $end
    $var wire 8 ( data_buf [7:0] $end
   $upscope $end
  $upscope $end
 $upscope $end
$enddefinitions $end


#0
0#
0$
b00 %
b00000000 &
b000 '
b00000000 (
0)
0*
0+
b00000000 ,
b00000000000000000000000011011001 -
b00 .
b01 /
b10 0
b11 1
#20000
1#
1)
#40000
0)
#60000
1)
#80000
0)
#100000
1)
1*
#120000
0)
#140000
1)
#160000
0)
#180000
1)
#200000
0)
1+
b00111100 ,
#220000
1$
b01 %
b00111100 (
1)
#240000
0)
0+
#260000
0#
b00000001 &
1)
#280000
0)
#300000
b00000010 &
1)
#320000
0)
#340000
b00000011 &
1)
#360000
0)
#380000
b00000100 &
1)
#400000
0)
#420000
b00000101 &
1)
#440000
0)
#460000
b00000110 &
1)
#480000
0)
#500000
b00000111 &
1)
#520000
0)
#540000
b00001000 &
1)
#560000
0)
#580000
b00001001 &
1)
#600000
0)
#620000
b00001010 &
1)
#640000
0)
#660000
b00001011 &
1)
#680000
0)
#700000
b00001100 &
1)
#720000
0)
#740000
b00001101 &
1)
#760000
0)
#780000
b00001110 &
1)
#800000
0)
#820000
b00001111 &
1)
#840000
0)
#860000
b00010000 &
1)
#880000
0)
#900000
b00010001 &
1)
#920000
0)
#940000
b00010010 &
1)
#960000
0)
#980000
b00010011 &
1)
#1000000
0)
#1020000
b00010100 &
1)
#1040000
0)
#1060000
b00010101 &
1)
#1080000
0)
#1100000
b00010110 &
1)
#1120000
0)
#1140000
b00010111 &
1)
#1160000
0)
#1180000
b00011000 &
1)
#1200000
0)
#1220000
b00011001 &
1)
#1240000
0)
#1260000
b00011010 &
1)
#1280000
0)
#1300000
b00011011 &
1)
#1320000
0)
#1340000
b00011100 &
1)
#1360000
0)
#1380000
b00011101 &
1)
#1400000
0)
#1420000
b00011110 &
1)
#1440000
0)
#1460000
b00011111 &
1)
#1480000
0)
#1500000
b00100000 &
1)
#1520000
0)
#1540000
b00100001 &
1)
#1560000
0)
#1580000
b00100010 &
1)
#1600000
0)
#1620000
b00100011 &
1)
#1640000
0)
#1660000
b00100100 &
1)
#1680000
0)
#1700000
b00100101 &
1)
#1720000
0)
#1740000
b00100110 &
1)
#1760000
0)
#1780000
b00100111 &
1)
#1800000
0)
#1820000
b00101000 &
1)
#1840000
0)
#1860000
b00101001 &
1)
#1880000
0)
#1900000
b00101010 &
1)
#1920000
0)
#1940000
b00101011 &
1)
#1960000
0)
#1980000
b00101100 &
1)
#2000000
0)
#2020000
b00101101 &
1)
#2040000
0)
#2060000
b00101110 &
1)
#2080000
0)
#2100000
b00101111 &
1)
#2120000
0)
#2140000
b00110000 &
1)
#2160000
0)
#2180000
b00110001 &
1)
#2200000
0)
#2220000
b00110010 &
1)
#2240000
0)
#2260000
b00110011 &
1)
#2280000
0)
#2300000
b00110100 &
1)
#2320000
0)
#2340000
b00110101 &
1)
#2360000
0)
#2380000
b00110110 &
1)
#2400000
0)
#2420000
b00110111 &
1)
#2440000
0)
#2460000
b00111000 &
1)
#2480000
0)
#2500000
b00111001 &
1)
#2520000
0)
#2540000
b00111010 &
1)
#2560000
0)
#2580000
b00111011 &
1)
#2600000
0)
#2620000
b00111100 &
1)
#2640000
0)
#2660000
b00111101 &
1)
#2680000
0)
#2700000
b00111110 &
1)
#2720000
0)
#2740000
b00111111 &
1)
#2760000
0)
#2780000
b01000000 &
1)
#2800000
0)
#2820000
b01000001 &
1)
#2840000
0)
#2860000
b01000010 &
1)
#2880000
0)
#2900000
b01000011 &
1)
#2920000
0)
#2940000
b01000100 &
1)
#2960000
0)
#2980000
b01000101 &
1)
#3000000
0)
#3020000
b01000110 &
1)
#3040000
0)
#3060000
b01000111 &
1)
#3080000
0)
#3100000
b01001000 &
1)
#3120000
0)
#3140000
b01001001 &
1)
#3160000
0)
#3180000
b01001010 &
1)
#3200000
0)
#3220000
b01001011 &
1)
#3240000
0)
#3260000
b01001100 &
1)
#3280000
0)
#3300000
b01001101 &
1)
#3320000
0)
#3340000
b01001110 &
1)
#3360000
0)
#3380000
b01001111 &
1)
#3400000
0)
#3420000
b01010000 &
1)
#3440000
0)
#3460000
b01010001 &
1)
#3480000
0)
#3500000
b01010010 &
1)
#3520000
0)
#3540000
b01010011 &
1)
#3560000
0)
#3580000
b01010100 &
1)
#3600000
0)
#3620000
b01010101 &
1)
#3640000
0)
#3660000
b01010110 &
1)
#3680000
0)
#3700000
b01010111 &
1)
#3720000
0)
#3740000
b01011000 &
1)
#3760000
0)
#3780000
b01011001 &
1)
#3800000
0)
#3820000
b01011010 &
1)
#3840000
0)
#3860000
b01011011 &
1)
#3880000
0)
#3900000
b01011100 &
1)
#3920000
0)
#3940000
b01011101 &
1)
#3960000
0)
#3980000
b01011110 &
1)
#4000000
0)
#4020000
b01011111 &
1)
#4040000
0)
#4060000
b01100000 &
1)
#4080000
0)
#4100000
b01100001 &
1)
#4120000
0)
#4140000
b01100010 &
1)
#4160000
0)
#4180000
b01100011 &
1)
#4200000
0)
#4220000
b01100100 &
1)
#4240000
0)
#4260000
b01100101 &
1)
#4280000
0)
#4300000
b01100110 &
1)
#4320000
0)
#4340000
b01100111 &
1)
#4360000
0)
#4380000
b01101000 &
1)
#4400000
0)
#4420000
b01101001 &
1)
#4440000
0)
#4460000
b01101010 &
1)
#4480000
0)
#4500000
b01101011 &
1)
#4520000
0)
#4540000
b01101100 &
1)
#4560000
0)
#4580000
b01101101 &
1)
#4600000
0)
#4620000
b01101110 &
1)
#4640000
0)
#4660000
b01101111 &
1)
#4680000
0)
#4700000
b01110000 &
1)
#4720000
0)
#4740000
b01110001 &
1)
#4760000
0)
#4780000
b01110010 &
1)
#4800000
0)
#4820000
b01110011 &
1)
#4840000
0)
#4860000
b01110100 &
1)
#4880000
0)
#4900000
b01110101 &
1)
#4920000
0)
#4940000
b01110110 &
1)
#4960000
0)
#4980000
b01110111 &
1)
#5000000
0)
#5020000
b01111000 &
1)
#5040000
0)
#5060000
b01111001 &
1)
#5080000
0)
#5100000
b01111010 &
1)
#5120000
0)
#5140000
b01111011 &
1)
#5160000
0)
#5180000
b01111100 &
1)
#5200000
0)
#5220000
b01111101 &
1)
#5240000
0)
#5260000
b01111110 &
1)
#5280000
0)
#5300000
b01111111 &
1)
#5320000
0)
#5340000
b10000000 &
1)
#5360000
0)
#5380000
b10000001 &
1)
#5400000
0)
#5420000
b10000010 &
1)
#5440000
0)
#5460000
b10000011 &
1)
#5480000
0)
#5500000
b10000100 &
1)
#5520000
0)
#5540000
b10000101 &
1)
#5560000
0)
#5580000
b10000110 &
1)
#5600000
0)
#5620000
b10000111 &
1)
#5640000
0)
#5660000
b10001000 &
1)
#5680000
0)
#5700000
b10001001 &
1)
#5720000
0)
#5740000
b10001010 &
1)
#5760000
0)
#5780000
b10001011 &
1)
#5800000
0)
#5820000
b10001100 &
1)
#5840000
0)
#5860000
b10001101 &
1)
#5880000
0)
#5900000
b10001110 &
1)
#5920000
0)
#5940000
b10001111 &
1)
#5960000
0)
#5980000
b10010000 &
1)
#6000000
0)
#6020000
b10010001 &
1)
#6040000
0)
#6060000
b10010010 &
1)
#6080000
0)
#6100000
b10010011 &
1)
#6120000
0)
#6140000
b10010100 &
1)
#6160000
0)
#6180000
b10010101 &
1)
#6200000
0)
#6220000
b10010110 &
1)
#6240000
0)
#6260000
b10010111 &
1)
#6280000
0)
#6300000
b10011000 &
1)
#6320000
0)
#6340000
b10011001 &
1)
#6360000
0)
#6380000
b10011010 &
1)
#6400000
0)
#6420000
b10011011 &
1)
#6440000
0)
#6460000
b10011100 &
1)
#6480000
0)
#6500000
b10011101 &
1)
#6520000
0)
#6540000
b10011110 &
1)
#6560000
0)
#6580000
b10011111 &
1)
#6600000
0)
#6620000
b10100000 &
1)
#6640000
0)
#6660000
b10100001 &
1)
#6680000
0)
#6700000
b10100010 &
1)
#6720000
0)
#6740000
b10100011 &
1)
#6760000
0)
#6780000
b10100100 &
1)
#6800000
0)
#6820000
b10100101 &
1)
#6840000
0)
#6860000
b10100110 &
1)
#6880000
0)
#6900000
b10100111 &
1)
#6920000
0)
#6940000
b10101000 &
1)
#6960000
0)
#6980000
b10101001 &
1)
#7000000
0)
#7020000
b10101010 &
1)
#7040000
0)
#7060000
b10101011 &
1)
#7080000
0)
#7100000
b10101100 &
1)
#7120000
0)
#7140000
b10101101 &
1)
#7160000
0)
#7180000
b10101110 &
1)
#7200000
0)
#7220000
b10101111 &
1)
#7240000
0)
#7260000
b10110000 &
1)
#7280000
0)
#7300000
b10110001 &
1)
#7320000
0)
#7340000
b10110010 &
1)
#7360000
0)
#7380000
b10110011 &
1)
#7400000
0)
#7420000
b10110100 &
1)
#7440000
0)
#7460000
b10110101 &
1)
#7480000
0)
#7500000
b10110110 &
1)
#7520000
0)
#7540000
b10110111 &
1)
#7560000
0)
#7580000
b10111000 &
1)
#7600000
0)
#7620000
b10111001 &
1)
#7640000
0)
#7660000
b10111010 &
1)
#7680000
0)
#7700000
b10111011 &
1)
#7720000
0)
#7740000
b10111100 &
1)
#7760000
0)
#7780000
b10111101 &
1)
#7800000
0)
#7820000
b10111110 &
1)
#7840000
0)
#7860000
b10111111 &
1)
#7880000
0)
#7900000
b11000000 &
1)
#7920000
0)
#7940000
b11000001 &
1)
#7960000
0)
#7980000
b11000010 &
1)
#8000000
0)
#8020000
b11000011 &
1)
#8040000
0)
#8060000
b11000100 &
1)
#8080000
0)
#8100000
b11000101 &
1)
#8120000
0)
#8140000
b11000110 &
1)
#8160000
0)
#8180000
b11000111 &
1)
#8200000
0)
#8220000
b11001000 &
1)
#8240000
0)
#8260000
b11001001 &
1)
#8280000
0)
#8300000
b11001010 &
1)
#8320000
0)
#8340000
b11001011 &
1)
#8360000
0)
#8380000
b11001100 &
1)
#8400000
0)
#8420000
b11001101 &
1)
#8440000
0)
#8460000
b11001110 &
1)
#8480000
0)
#8500000
b11001111 &
1)
#8520000
0)
#8540000
b11010000 &
1)
#8560000
0)
#8580000
b11010001 &
1)
#8600000
0)
#8620000
b11010010 &
1)
#8640000
0)
#8660000
b11010011 &
1)
#8680000
0)
#8700000
b11010100 &
1)
#8720000
0)
#8740000
b11010101 &
1)
#8760000
0)
#8780000
b11010110 &
1)
#8800000
0)
#8820000
b11010111 &
1)
#8840000
0)
#8860000
b11011000 &
1)
#8880000
0)
#8900000
b10 %
b00000000 &
1)
#8920000
0)
#8940000
b00000001 &
1)
#8960000
0)
#8980000
b00000010 &
1)
#9000000
0)
#9020000
b00000011 &
1)
#9040000
0)
#9060000
b00000100 &
1)
#9080000
0)
#9100000
b00000101 &
1)
#9120000
0)
#9140000
b00000110 &
1)
#9160000
0)
#9180000
b00000111 &
1)
#9200000
0)
#9220000
b00001000 &
1)
#9240000
0)
#9260000
b00001001 &
1)
#9280000
0)
#9300000
b00001010 &
1)
#9320000
0)
#9340000
b00001011 &
1)
#9360000
0)
#9380000
b00001100 &
1)
#9400000
0)
#9420000
b00001101 &
1)
#9440000
0)
#9460000
b00001110 &
1)
#9480000
0)
#9500000
b00001111 &
1)
#9520000
0)
#9540000
b00010000 &
1)
#9560000
0)
#9580000
b00010001 &
1)
#9600000
0)
#9620000
b00010010 &
1)
#9640000
0)
#9660000
b00010011 &
1)
#9680000
0)
#9700000
b00010100 &
1)
#9720000
0)
#9740000
b00010101 &
1)
#9760000
0)
#9780000
b00010110 &
1)
#9800000
0)
#9820000
b00010111 &
1)
#9840000
0)
#9860000
b00011000 &
1)
#9880000
0)
#9900000
b00011001 &
1)
#9920000
0)
#9940000
b00011010 &
1)
#9960000
0)
#9980000
b00011011 &
1)
#10000000
0)
#10020000
b00011100 &
1)
#10040000
0)
#10060000
b00011101 &
1)
#10080000
0)
#10100000
b00011110 &
1)
#10120000
0)
#10140000
b00011111 &
1)
#10160000
0)
#10180000
b00100000 &
1)
#10200000
0)
#10220000
b00100001 &
1)
#10240000
0)
#10260000
b00100010 &
1)
#10280000
0)
#10300000
b00100011 &
1)
#10320000
0)
#10340000
b00100100 &
1)
#10360000
0)
#10380000
b00100101 &
1)
#10400000
0)
#10420000
b00100110 &
1)
#10440000
0)
#10460000
b00100111 &
1)
#10480000
0)
#10500000
b00101000 &
1)
#10520000
0)
#10540000
b00101001 &
1)
#10560000
0)
#10580000
b00101010 &
1)
#10600000
0)
#10620000
b00101011 &
1)
#10640000
0)
#10660000
b00101100 &
1)
#10680000
0)
#10700000
b00101101 &
1)
#10720000
0)
#10740000
b00101110 &
1)
#10760000
0)
#10780000
b00101111 &
1)
#10800000
0)
#10820000
b00110000 &
1)
#10840000
0)
#10860000
b00110001 &
1)
#10880000
0)
#10900000
b00110010 &
1)
#10920000
0)
#10940000
b00110011 &
1)
#10960000
0)
#10980000
b00110100 &
1)
#11000000
0)
#11020000
b00110101 &
1)
#11040000
0)
#11060000
b00110110 &
1)
#11080000
0)
#11100000
b00110111 &
1)
#11120000
0)
#11140000
b00111000 &
1)
#11160000
0)
#11180000
b00111001 &
1)
#11200000
0)
#11220000
b00111010 &
1)
#11240000
0)
#11260000
b00111011 &
1)
#11280000
0)
#11300000
b00111100 &
1)
#11320000
0)
#11340000
b00111101 &
1)
#11360000
0)
#11380000
b00111110 &
1)
#11400000
0)
#11420000
b00111111 &
1)
#11440000
0)
#11460000
b01000000 &
1)
#11480000
0)
#11500000
b01000001 &
1)
#11520000
0)
#11540000
b01000010 &
1)
#11560000
0)
#11580000
b01000011 &
1)
#11600000
0)
#11620000
b01000100 &
1)
#11640000
0)
#11660000
b01000101 &
1)
#11680000
0)
#11700000
b01000110 &
1)
#11720000
0)
#11740000
b01000111 &
1)
#11760000
0)
#11780000
b01001000 &
1)
#11800000
0)
#11820000
b01001001 &
1)
#11840000
0)
#11860000
b01001010 &
1)
#11880000
0)
#11900000
b01001011 &
1)
#11920000
0)
#11940000
b01001100 &
1)
#11960000
0)
#11980000
b01001101 &
1)
#12000000
0)
#12020000
b01001110 &
1)
#12040000
0)
#12060000
b01001111 &
1)
#12080000
0)
#12100000
b01010000 &
1)
#12120000
0)
#12140000
b01010001 &
1)
#12160000
0)
#12180000
b01010010 &
1)
#12200000
0)
#12220000
b01010011 &
1)
#12240000
0)
#12260000
b01010100 &
1)
#12280000
0)
#12300000
b01010101 &
1)
#12320000
0)
#12340000
b01010110 &
1)
#12360000
0)
#12380000
b01010111 &
1)
#12400000
0)
#12420000
b01011000 &
1)
#12440000
0)
#12460000
b01011001 &
1)
#12480000
0)
#12500000
b01011010 &
1)
#12520000
0)
#12540000
b01011011 &
1)
#12560000
0)
#12580000
b01011100 &
1)
#12600000
0)
#12620000
b01011101 &
1)
#12640000
0)
#12660000
b01011110 &
1)
#12680000
0)
#12700000
b01011111 &
1)
#12720000
0)
#12740000
b01100000 &
1)
#12760000
0)
#12780000
b01100001 &
1)
#12800000
0)
#12820000
b01100010 &
1)
#12840000
0)
#12860000
b01100011 &
1)
#12880000
0)
#12900000
b01100100 &
1)
#12920000
0)
#12940000
b01100101 &
1)
#12960000
0)
#12980000
b01100110 &
1)
#13000000
0)
#13020000
b01100111 &
1)
#13040000
0)
#13060000
b01101000 &
1)
#13080000
0)
#13100000
b01101001 &
1)
#13120000
0)
#13140000
b01101010 &
1)
#13160000
0)
#13180000
b01101011 &
1)
#13200000
0)
#13220000
b01101100 &
1)
#13240000
0)
#13260000
b01101101 &
1)
#13280000
0)
#13300000
b01101110 &
1)
#13320000
0)
#13340000
b01101111 &
1)
#13360000
0)
#13380000
b01110000 &
1)
#13400000
0)
#13420000
b01110001 &
1)
#13440000
0)
#13460000
b01110010 &
1)
#13480000
0)
#13500000
b01110011 &
1)
#13520000
0)
#13540000
b01110100 &
1)
#13560000
0)
#13580000
b01110101 &
1)
#13600000
0)
#13620000
b01110110 &
1)
#13640000
0)
#13660000
b01110111 &
1)
#13680000
0)
#13700000
b01111000 &
1)
#13720000
0)
#13740000
b01111001 &
1)
#13760000
0)
#13780000
b01111010 &
1)
#13800000
0)
#13820000
b01111011 &
1)
#13840000
0)
#13860000
b01111100 &
1)
#13880000
0)
#13900000
b01111101 &
1)
#13920000
0)
#13940000
b01111110 &
1)
#13960000
0)
#13980000
b01111111 &
1)
#14000000
0)
#14020000
b10000000 &
1)
#14040000
0)
#14060000
b10000001 &
1)
#14080000
0)
#14100000
b10000010 &
1)
#14120000
0)
#14140000
b10000011 &
1)
#14160000
0)
#14180000
b10000100 &
1)
#14200000
0)
#14220000
b10000101 &
1)
#14240000
0)
#14260000
b10000110 &
1)
#14280000
0)
#14300000
b10000111 &
1)
#14320000
0)
#14340000
b10001000 &
1)
#14360000
0)
#14380000
b10001001 &
1)
#14400000
0)
#14420000
b10001010 &
1)
#14440000
0)
#14460000
b10001011 &
1)
#14480000
0)
#14500000
b10001100 &
1)
#14520000
0)
#14540000
b10001101 &
1)
#14560000
0)
#14580000
b10001110 &
1)
#14600000
0)
#14620000
b10001111 &
1)
#14640000
0)
#14660000
b10010000 &
1)
#14680000
0)
#14700000
b10010001 &
1)
#14720000
0)
#14740000
b10010010 &
1)
#14760000
0)
#14780000
b10010011 &
1)
#14800000
0)
#14820000
b10010100 &
1)
#14840000
0)
#14860000
b10010101 &
1)
#14880000
0)
#14900000
b10010110 &
1)
#14920000
0)
#14940000
b10010111 &
1)
#14960000
0)
#14980000
b10011000 &
1)
#15000000
0)
#15020000
b10011001 &
1)
#15040000
0)
#15060000
b10011010 &
1)
#15080000
0)
#15100000
b10011011 &
1)
#15120000
0)
#15140000
b10011100 &
1)
#15160000
0)
#15180000
b10011101 &
1)
#15200000
0)
#15220000
b10011110 &
1)
#15240000
0)
#15260000
b10011111 &
1)
#15280000
0)
#15300000
b10100000 &
1)
#15320000
0)
#15340000
b10100001 &
1)
#15360000
0)
#15380000
b10100010 &
1)
#15400000
0)
#15420000
b10100011 &
1)
#15440000
0)
#15460000
b10100100 &
1)
#15480000
0)
#15500000
b10100101 &
1)
#15520000
0)
#15540000
b10100110 &
1)
#15560000
0)
#15580000
b10100111 &
1)
#15600000
0)
#15620000
b10101000 &
1)
#15640000
0)
#15660000
b10101001 &
1)
#15680000
0)
#15700000
b10101010 &
1)
#15720000
0)
#15740000
b10101011 &
1)
#15760000
0)
#15780000
b10101100 &
1)
#15800000
0)
#15820000
b10101101 &
1)
#15840000
0)
#15860000
b10101110 &
1)
#15880000
0)
#15900000
b10101111 &
1)
#15920000
0)
#15940000
b10110000 &
1)
#15960000
0)
#15980000
b10110001 &
1)
#16000000
0)
#16020000
b10110010 &
1)
#16040000
0)
#16060000
b10110011 &
1)
#16080000
0)
#16100000
b10110100 &
1)
#16120000
0)
#16140000
b10110101 &
1)
#16160000
0)
#16180000
b10110110 &
1)
#16200000
0)
#16220000
b10110111 &
1)
#16240000
0)
#16260000
b10111000 &
1)
#16280000
0)
#16300000
b10111001 &
1)
#16320000
0)
#16340000
b10111010 &
1)
#16360000
0)
#16380000
b10111011 &
1)
#16400000
0)
#16420000
b10111100 &
1)
#16440000
0)
#16460000
b10111101 &
1)
#16480000
0)
#16500000
b10111110 &
1)
#16520000
0)
#16540000
b10111111 &
1)
#16560000
0)
#16580000
b11000000 &
1)
#16600000
0)
#16620000
b11000001 &
1)
#16640000
0)
#16660000
b11000010 &
1)
#16680000
0)
#16700000
b11000011 &
1)
#16720000
0)
#16740000
b11000100 &
1)
#16760000
0)
#16780000
b11000101 &
1)
#16800000
0)
#16820000
b11000110 &
1)
#16840000
0)
#16860000
b11000111 &
1)
#16880000
0)
#16900000
b11001000 &
1)
#16920000
0)
#16940000
b11001001 &
1)
#16960000
0)
#16980000
b11001010 &
1)
#17000000
0)
#17020000
b11001011 &
1)
#17040000
0)
#17060000
b11001100 &
1)
#17080000
0)
#17100000
b11001101 &
1)
#17120000
0)
#17140000
b11001110 &
1)
#17160000
0)
#17180000
b11001111 &
1)
#17200000
0)
#17220000
b11010000 &
1)
#17240000
0)
#17260000
b11010001 &
1)
#17280000
0)
#17300000
b11010010 &
1)
#17320000
0)
#17340000
b11010011 &
1)
#17360000
0)
#17380000
b11010100 &
1)
#17400000
0)
#17420000
b11010101 &
1)
#17440000
0)
#17460000
b11010110 &
1)
#17480000
0)
#17500000
b11010111 &
1)
#17520000
0)
#17540000
b11011000 &
1)
#17560000
0)
#17580000
b00000000 &
b001 '
1)
#17600000
0)
#17620000
b00000001 &
1)
#17640000
0)
#17660000
b00000010 &
1)
#17680000
0)
#17700000
b00000011 &
1)
#17720000
0)
#17740000
b00000100 &
1)
#17760000
0)
#17780000
b00000101 &
1)
#17800000
0)
#17820000
b00000110 &
1)
#17840000
0)
#17860000
b00000111 &
1)
#17880000
0)
#17900000
b00001000 &
1)
#17920000
0)
#17940000
b00001001 &
1)
#17960000
0)
#17980000
b00001010 &
1)
#18000000
0)
#18020000
b00001011 &
1)
#18040000
0)
#18060000
b00001100 &
1)
#18080000
0)
#18100000
b00001101 &
1)
#18120000
0)
#18140000
b00001110 &
1)
#18160000
0)
#18180000
b00001111 &
1)
#18200000
0)
#18220000
b00010000 &
1)
#18240000
0)
#18260000
b00010001 &
1)
#18280000
0)
#18300000
b00010010 &
1)
#18320000
0)
#18340000
b00010011 &
1)
#18360000
0)
#18380000
b00010100 &
1)
#18400000
0)
#18420000
b00010101 &
1)
#18440000
0)
#18460000
b00010110 &
1)
#18480000
0)
#18500000
b00010111 &
1)
#18520000
0)
#18540000
b00011000 &
1)
#18560000
0)
#18580000
b00011001 &
1)
#18600000
0)
#18620000
b00011010 &
1)
#18640000
0)
#18660000
b00011011 &
1)
#18680000
0)
#18700000
b00011100 &
1)
#18720000
0)
#18740000
b00011101 &
1)
#18760000
0)
#18780000
b00011110 &
1)
#18800000
0)
#18820000
b00011111 &
1)
#18840000
0)
#18860000
b00100000 &
1)
#18880000
0)
#18900000
b00100001 &
1)
#18920000
0)
#18940000
b00100010 &
1)
#18960000
0)
#18980000
b00100011 &
1)
#19000000
0)
#19020000
b00100100 &
1)
#19040000
0)
#19060000
b00100101 &
1)
#19080000
0)
#19100000
b00100110 &
1)
#19120000
0)
#19140000
b00100111 &
1)
#19160000
0)
#19180000
b00101000 &
1)
#19200000
0)
#19220000
b00101001 &
1)
#19240000
0)
#19260000
b00101010 &
1)
#19280000
0)
#19300000
b00101011 &
1)
#19320000
0)
#19340000
b00101100 &
1)
#19360000
0)
#19380000
b00101101 &
1)
#19400000
0)
#19420000
b00101110 &
1)
#19440000
0)
#19460000
b00101111 &
1)
#19480000
0)
#19500000
b00110000 &
1)
#19520000
0)
#19540000
b00110001 &
1)
#19560000
0)
#19580000
b00110010 &
1)
#19600000
0)
#19620000
b00110011 &
1)
#19640000
0)
#19660000
b00110100 &
1)
#19680000
0)
#19700000
b00110101 &
1)
#19720000
0)
#19740000
b00110110 &
1)
#19760000
0)
#19780000
b00110111 &
1)
#19800000
0)
#19820000
b00111000 &
1)
#19840000
0)
#19860000
b00111001 &
1)
#19880000
0)
#19900000
b00111010 &
1)
#19920000
0)
#19940000
b00111011 &
1)
#19960000
0)
#19980000
b00111100 &
1)
#20000000
0)
#20020000
b00111101 &
1)
#20040000
0)
#20060000
b00111110 &
1)
#20080000
0)
#20100000
b00111111 &
1)
#20120000
0)
#20140000
b01000000 &
1)
#20160000
0)
#20180000
b01000001 &
1)
#20200000
0)
#20220000
b01000010 &
1)
#20240000
0)
#20260000
b01000011 &
1)
#20280000
0)
#20300000
b01000100 &
1)
#20320000
0)
#20340000
b01000101 &
1)
#20360000
0)
#20380000
b01000110 &
1)
#20400000
0)
#20420000
b01000111 &
1)
#20440000
0)
#20460000
b01001000 &
1)
#20480000
0)
#20500000
b01001001 &
1)
#20520000
0)
#20540000
b01001010 &
1)
#20560000
0)
#20580000
b01001011 &
1)
#20600000
0)
#20620000
b01001100 &
1)
#20640000
0)
#20660000
b01001101 &
1)
#20680000
0)
#20700000
b01001110 &
1)
#20720000
0)
#20740000
b01001111 &
1)
#20760000
0)
#20780000
b01010000 &
1)
#20800000
0)
#20820000
b01010001 &
1)
#20840000
0)
#20860000
b01010010 &
1)
#20880000
0)
#20900000
b01010011 &
1)
#20920000
0)
#20940000
b01010100 &
1)
#20960000
0)
#20980000
b01010101 &
1)
#21000000
0)
#21020000
b01010110 &
1)
#21040000
0)
#21060000
b01010111 &
1)
#21080000
0)
#21100000
b01011000 &
1)
#21120000
0)
#21140000
b01011001 &
1)
#21160000
0)
#21180000
b01011010 &
1)
#21200000
0)
#21220000
b01011011 &
1)
#21240000
0)
#21260000
b01011100 &
1)
#21280000
0)
#21300000
b01011101 &
1)
#21320000
0)
#21340000
b01011110 &
1)
#21360000
0)
#21380000
b01011111 &
1)
#21400000
0)
#21420000
b01100000 &
1)
#21440000
0)
#21460000
b01100001 &
1)
#21480000
0)
#21500000
b01100010 &
1)
#21520000
0)
#21540000
b01100011 &
1)
#21560000
0)
#21580000
b01100100 &
1)
#21600000
0)
#21620000
b01100101 &
1)
#21640000
0)
#21660000
b01100110 &
1)
#21680000
0)
#21700000
b01100111 &
1)
#21720000
0)
#21740000
b01101000 &
1)
#21760000
0)
#21780000
b01101001 &
1)
#21800000
0)
#21820000
b01101010 &
1)
#21840000
0)
#21860000
b01101011 &
1)
#21880000
0)
#21900000
b01101100 &
1)
#21920000
0)
#21940000
b01101101 &
1)
#21960000
0)
#21980000
b01101110 &
1)
#22000000
0)
#22020000
b01101111 &
1)
#22040000
0)
#22060000
b01110000 &
1)
#22080000
0)
#22100000
b01110001 &
1)
#22120000
0)
#22140000
b01110010 &
1)
#22160000
0)
#22180000
b01110011 &
1)
#22200000
0)
#22220000
b01110100 &
1)
#22240000
0)
#22260000
b01110101 &
1)
#22280000
0)
#22300000
b01110110 &
1)
#22320000
0)
#22340000
b01110111 &
1)
#22360000
0)
#22380000
b01111000 &
1)
#22400000
0)
#22420000
b01111001 &
1)
#22440000
0)
#22460000
b01111010 &
1)
#22480000
0)
#22500000
b01111011 &
1)
#22520000
0)
#22540000
b01111100 &
1)
#22560000
0)
#22580000
b01111101 &
1)
#22600000
0)
