uart_project/rtl/uart_rx.v
`timescale 1ns/1ps

module uart_rx
#(
    parameter CLKS_PER_BIT = 217
)
(
    input  wire       clk,
    input  wire       rst_n,
    input  wire       serial_in,

    output reg [7:0] data_out,
    output reg       data_ready
);

localparam IDLE  = 2'd0;
localparam START = 2'd1;
localparam RECV  = 2'd2;
localparam STOP  = 2'd3;

reg [1:0] state;

reg [7:0] clk_count;
reg [2:0] bit_index;
reg [7:0] data_buf;

// Synchronizer
reg rx_meta;
reg rx_sync;

always @(posedge clk)
begin
    rx_meta <= serial_in;
    rx_sync <= rx_meta;
end

always @(posedge clk)
begin
    if(!rst_n)
    begin
        state      <= IDLE;
        clk_count  <= 0;
        bit_index  <= 0;
        data_buf   <= 0;
        data_out   <= 0;
        data_ready <= 0;
    end
    else
    begin

        data_ready <= 1'b0;

        case(state)

        //--------------------------------
        IDLE:
        //--------------------------------
        begin
            clk_count <= 0;
            bit_index <= 0;

            if(rx_sync == 1'b0)
                state <= START;
        end

        //--------------------------------
        START:
        //--------------------------------
        begin
            if(clk_count == (CLKS_PER_BIT/2))
            begin
                clk_count <= 0;

                if(rx_sync == 1'b0)
                    state <= RECV;
                else
                    state <= IDLE;
            end
            else
                clk_count <= clk_count + 1;
        end

        //--------------------------------
        RECV:
        //--------------------------------
        begin
            if(clk_count == CLKS_PER_BIT-1)
            begin
                clk_count <= 0;

                data_buf[bit_index] <= rx_sync;

                if(bit_index == 3'd7)
                begin
                    bit_index <= 0;
                    state <= STOP;
                end
                else
                    bit_index <= bit_index + 1;
            end
            else
                clk_count <= clk_count + 1;
        end

        //--------------------------------
        STOP:
        //--------------------------------
        begin
            if(clk_count == CLKS_PER_BIT-1)
            begin
                clk_count <= 0;

                if(rx_sync == 1'b1)
                begin
                    data_out <= data_buf;
                    data_ready <= 1'b1;
                end

                state <= IDLE;
            end
            else
                clk_count <= clk_count + 1;
        end

        default:
            state <= IDLE;

        endcase
    end
end

endmodule

uart_project/rtl/uart_tx.v
`timescale 1ns/1ps

module uart_tx
#(
    parameter CLKS_PER_BIT = 217
)
(
    input  wire       clk,
    input  wire       rst_n,
    input  wire       tx_start,
    input  wire [7:0] tx_data,

    output reg        tx,
    output reg        tx_busy
);

localparam IDLE  = 2'd0;
localparam START = 2'd1;
localparam DATA  = 2'd2;
localparam STOP  = 2'd3;

reg [1:0] state;
reg [7:0] clk_count;
reg [2:0] bit_index;
reg [7:0] data_buf;

always @(posedge clk)
begin
    if(!rst_n)
    begin
        state      <= IDLE;
        tx         <= 1'b1;
        tx_busy    <= 1'b0;
        clk_count  <= 8'd0;
        bit_index  <= 3'd0;
        data_buf   <= 8'd0;
    end
    else
    begin

        case(state)

        //--------------------------------
        IDLE:
        //--------------------------------
        begin
            tx <= 1'b1;
            tx_busy <= 1'b0;

            if(tx_start)
            begin
                data_buf <= tx_data;
                state <= START;
                tx_busy <= 1'b1;
            end
        end

        //--------------------------------
        START:
        //--------------------------------
        begin
            tx <= 1'b0;

            if(clk_count == CLKS_PER_BIT-1)
            begin
                clk_count <= 0;
                state <= DATA;
            end
            else
                clk_count <= clk_count + 1;
        end

        //--------------------------------
        DATA:
        //--------------------------------
        begin
            tx <= data_buf[bit_index];

            if(clk_count == CLKS_PER_BIT-1)
            begin
                clk_count <= 0;

                if(bit_index == 7)
                begin
                    bit_index <= 0;
                    state <= STOP;
                end
                else
                    bit_index <= bit_index + 1;
            end
            else
                clk_count <= clk_count + 1;
        end

        //--------------------------------
        STOP:
        //--------------------------------
        begin
            tx <= 1'b1;

            if(clk_count == CLKS_PER_BIT-1)
            begin
                clk_count <= 0;
                tx_busy <= 1'b0;
                state <= IDLE;
            end
            else
                clk_count <= clk_count + 1;
        end

        default:
            state <= IDLE;

        endcase
    end
end

endmodule

uart_project/rtl/uart_controller.v
`timescale 1ns/1ps

module uart_controller
#(
    parameter CLKS_PER_BIT = 217
)
(
    input wire clk,
    input wire rst_n,

    // TX Interface
    input wire tx_start,
    input wire [7:0] tx_data,

    // RX Serial Input
    input wire rx,

    // UART Pins
    output wire tx,

    // RX Output
    output wire [7:0] rx_data,
    output wire rx_ready,

    // TX Status
    output wire tx_busy
);

uart_tx #(
    .CLKS_PER_BIT(CLKS_PER_BIT)
)
u_tx
(
    .clk(clk),
    .rst_n(rst_n),
    .tx_start(tx_start),
    .tx_data(tx_data),
    .tx(tx),
    .tx_busy(tx_busy)
);

uart_rx #(
    .CLKS_PER_BIT(CLKS_PER_BIT)
)
u_rx
(
    .clk(clk),
    .rst_n(rst_n),
    .serial_in(rx),
    .data_out(rx_data),
    .data_ready(rx_ready)
);

endmodule

uart_project/tb/uart_controller_tb.v
`timescale 1ns/1ps

module uart_controller_tb;

localparam CLKS_PER_BIT = 217;

reg clk;
reg rst_n;

reg tx_start;
reg [7:0] tx_data;

wire tx;
wire tx_busy;

wire [7:0] rx_data;
wire rx_ready;

uart_controller #(
    .CLKS_PER_BIT(CLKS_PER_BIT)
)
dut
(
    .clk(clk),
    .rst_n(rst_n),

    .tx_start(tx_start),
    .tx_data(tx_data),

    .rx(tx),      // LOOPBACK

    .tx(tx),

    .rx_data(rx_data),
    .rx_ready(rx_ready),

    .tx_busy(tx_busy)
);

always #20 clk <= ~clk;

initial
begin

    clk = 0;
    rst_n = 0;

    tx_start = 0;
    tx_data  = 0;

    #100;

    rst_n = 1;

    #500;

    // Send 3C
    tx_data  = 8'h3C;
    tx_start = 1;

    #40;
    tx_start = 0;

    wait(tx_busy == 0);

    #50000;

    $finish;

end

always @(posedge clk)
begin
    if(rx_ready)
    begin
        $display("--------------------------------");
        $display("RX DATA = %h", rx_data);
        $display("--------------------------------");

        if(rx_data == 8'h3C)
            $display("TEST PASSED");
        else
            $display("TEST FAILED");
    end
end

initial
begin
    $dumpfile("uart_controller.vcd");
    $dumpvars(0, uart_controller_tb);
end

endmodule

uart_project/results/uart_controller.vcd
$version Generated by VerilatedVcd $end
$timescale 1ps $end
 $scope module TOP $end
  $scope module uart_controller_tb $end
   $var wire 32 5 CLKS_PER_BIT [31:0] $end
   $var wire 1 1 clk $end
   $var wire 1 2 rst_n $end
   $var wire 1 3 tx_start $end
   $var wire 8 4 tx_data [7:0] $end
   $var wire 1 # tx $end
   $var wire 1 $ tx_busy $end
   $var wire 8 % rx_data [7:0] $end
   $var wire 1 & rx_ready $end
   $scope module dut $end
    $var wire 32 5 CLKS_PER_BIT [31:0] $end
    $var wire 1 1 clk $end
    $var wire 1 2 rst_n $end
    $var wire 1 3 tx_start $end
    $var wire 8 4 tx_data [7:0] $end
    $var wire 1 # rx $end
    $var wire 1 # tx $end
    $var wire 8 % rx_data [7:0] $end
    $var wire 1 & rx_ready $end
    $var wire 1 $ tx_busy $end
    $scope module u_rx $end
     $var wire 32 5 CLKS_PER_BIT [31:0] $end
     $var wire 1 1 clk $end
     $var wire 1 2 rst_n $end
     $var wire 1 # serial_in $end
     $var wire 8 % data_out [7:0] $end
     $var wire 1 & data_ready $end
     $var wire 2 6 IDLE [1:0] $end
     $var wire 2 7 START [1:0] $end
     $var wire 2 8 RECV [1:0] $end
     $var wire 2 9 STOP [1:0] $end
     $var wire 2 ' state [1:0] $end
     $var wire 8 ( clk_count [7:0] $end
     $var wire 3 ) bit_index [2:0] $end
     $var wire 8 * data_buf [7:0] $end
     $var wire 1 + rx_meta $end
     $var wire 1 , rx_sync $end
    $upscope $end
    $scope module u_tx $end
     $var wire 32 5 CLKS_PER_BIT [31:0] $end
     $var wire 1 1 clk $end
     $var wire 1 2 rst_n $end
     $var wire 1 3 tx_start $end
     $var wire 8 4 tx_data [7:0] $end
     $var wire 1 # tx $end
     $var wire 1 $ tx_busy $end
     $var wire 2 6 IDLE [1:0] $end
     $var wire 2 7 START [1:0] $end
     $var wire 2 8 DATA [1:0] $end
     $var wire 2 9 STOP [1:0] $end
     $var wire 2 - state [1:0] $end
     $var wire 8 . clk_count [7:0] $end
     $var wire 3 / bit_index [2:0] $end
     $var wire 8 0 data_buf [7:0] $end
    $upscope $end
   $upscope $end
  $upscope $end
 $upscope $end
$enddefinitions $end


#0
0#
0$
b00000000 %
0&
b00 '
b00000000 (
b000 )
b00000000 *
0+
0,
b00 -
b00000000 .
b000 /
b00000000 0
01
02
03
b00000000 4
b00000000000000000000000011011001 5
b00 6
b01 7
b10 8
b11 9
#20000
1#
11
#40000
01
#60000
1+
11
#80000
01
#100000
b01 '
1,
11
12
#120000
01
#140000
b00000001 (
11
#160000
01
#180000
b00000010 (
11
#200000
01
#220000
b00000011 (
11
#240000
01
#260000
b00000100 (
11
#280000
01
#300000
b00000101 (
11
#320000
01
#340000
b00000110 (
11
#360000
01
#380000
b00000111 (
11
#400000
01
#420000
b00001000 (
11
#440000
01
#460000
b00001001 (
11
#480000
01
#500000
b00001010 (
11
#520000
01
#540000
b00001011 (
11
#560000
01
#580000
b00001100 (
11
#600000
01
13
b00111100 4
#620000
1$
b00001101 (
b01 -
b00111100 0
11
#640000
01
03
#660000
0#
b00001110 (
b00000001 .
11
#680000
01
#700000
b00001111 (
0+
b00000010 .
11
#720000
01
#740000
b00010000 (
0,
b00000011 .
11
#760000
01
#780000
b00010001 (
b00000100 .
11
#800000
01
#820000
b00010010 (
b00000101 .
11
#840000
01
#860000
b00010011 (
b00000110 .
11
#880000
01
#900000
b00010100 (
b00000111 .
11
#920000
01
#940000
b00010101 (
b00001000 .
11
#960000
01
#980000
b00010110 (
b00001001 .
11
#1000000
01
#1020000
b00010111 (
b00001010 .
11
#1040000
01
#1060000
b00011000 (
b00001011 .
11
#1080000
01
#1100000
b00011001 (
b00001100 .
11
#1120000
01
#1140000
b00011010 (
b00001101 .
11
#1160000
01
#1180000
b00011011 (
b00001110 .
11
#1200000
01
#1220000
b00011100 (
b00001111 .
11
#1240000
01
#1260000
b00011101 (
b00010000 .
11
#1280000
01
#1300000
b00011110 (
b00010001 .
11
#1320000
01
#1340000
b00011111 (
b00010010 .
11
#1360000
01
#1380000
b00100000 (
b00010011 .
11
#1400000
01
#1420000
b00100001 (
b00010100 .
11
#1440000
01
#1460000
b00100010 (
b00010101 .
11
#1480000
01
#1500000
b00100011 (
b00010110 .
11
#1520000
01
#1540000
b00100100 (
b00010111 .
11
#1560000
01
#1580000
b00100101 (
b00011000 .
11
#1600000
01
#1620000
b00100110 (
b00011001 .
11
#1640000
01
#1660000
b00100111 (
b00011010 .
11
#1680000
01
#1700000
b00101000 (
b00011011 .
11
#1720000
01
#1740000
b00101001 (
b00011100 .
11
#1760000
01
#1780000
b00101010 (
b00011101 .
11
#1800000
01
#1820000
b00101011 (
b00011110 .
11
#1840000
01
#1860000
b00101100 (
b00011111 .
11
#1880000
01
#1900000
b00101101 (
b00100000 .
11
#1920000
01
#1940000
b00101110 (
b00100001 .
11
#1960000
01
#1980000
b00101111 (
b00100010 .
11
#2000000
01
#2020000
b00110000 (
b00100011 .
11
#2040000
01
#2060000
b00110001 (
b00100100 .
11
#2080000
01
#2100000
b00110010 (
b00100101 .
11
#2120000
01
#2140000
b00110011 (
b00100110 .
11
#2160000
01
#2180000
b00110100 (
b00100111 .
11
#2200000
01
#2220000
b00110101 (
b00101000 .
11
#2240000
01
#2260000
b00110110 (
b00101001 .
11
#2280000
01
#2300000
b00110111 (
b00101010 .
11
#2320000
01
#2340000
b00111000 (
b00101011 .
11
#2360000
01
#2380000
b00111001 (
b00101100 .
11
#2400000
01
#2420000
b00111010 (
b00101101 .
11
#2440000
01
#2460000
b00111011 (
b00101110 .
11
#2480000
01
#2500000
b00111100 (
b00101111 .
11
#2520000
01
#2540000
b00111101 (
b00110000 .
11
#2560000
01
#2580000
b00111110 (
b00110001 .
11
#2600000
01
#2620000
b00111111 (
b00110010 .
11
#2640000
01
#2660000
b01000000 (
b00110011 .
11
#2680000
01
#2700000
b01000001 (
b00110100 .
11
#2720000
01
#2740000
b01000010 (
b00110101 .
11
#2760000
01
#2780000
b01000011 (
b00110110 .
11
#2800000
01
#2820000
b01000100 (
b00110111 .
11
#2840000
01
#2860000
b01000101 (
b00111000 .
11
#2880000
01
#2900000
b01000110 (
b00111001 .
11
#2920000
01
#2940000
b01000111 (
b00111010 .
11
#2960000
01
#2980000
b01001000 (
b00111011 .
11
#3000000
01
#3020000
b01001001 (
b00111100 .
11
#3040000
01
#3060000
b01001010 (
b00111101 .
11
#3080000
01
#3100000
b01001011 (
b00111110 .
11
#3120000
01
#3140000
b01001100 (
b00111111 .
11
#3160000
01
#3180000
b01001101 (
b01000000 .
11
#3200000
01
#3220000
b01001110 (
b01000001 .
11
#3240000
01
#3260000
b01001111 (
b01000010 .
11
#3280000
01
#3300000
b01010000 (
b01000011 .
11
#3320000
01
#3340000
b01010001 (
b01000100 .
11
#3360000
01
#3380000
b01010010 (
b01000101 .
11
#3400000
01
#3420000
b01010011 (
b01000110 .
11
#3440000
01
#3460000
b01010100 (
b01000111 .
11
#3480000
01
#3500000
b01010101 (
b01001000 .
11
#3520000
01
#3540000
b01010110 (
b01001001 .
11
#3560000
01
#3580000
b01010111 (
b01001010 .
11
#3600000
01
#3620000
b01011000 (
b01001011 .
11
#3640000
01
#3660000
b01011001 (
b01001100 .
11
#3680000
01
#3700000
b01011010 (
b01001101 .
11
#3720000
01
#3740000
b01011011 (
b01001110 .
11
#3760000
01
#3780000
b01011100 (
b01001111 .
11
#3800000
01
#3820000
b01011101 (
b01010000 .
11
#3840000
01
#3860000
b01011110 (
b01010001 .
11
#3880000
01
#3900000
b01011111 (
b01010010 .
11
#3920000
01
#3940000
b01100000 (
b01010011 .
11
#3960000
01
#3980000
b01100001 (
b01010100 .
11
#4000000
01
#4020000
b01100010 (
b01010101 .
11
#4040000
01
#4060000
b01100011 (
b01010110 .
11
#4080000
01
#4100000
b01100100 (
b01010111 .
11
#4120000
01
#4140000
b01100101 (
b01011000 .
11
#4160000
01
#4180000
b01100110 (
b01011001 .
11
#4200000
01
#4220000
b01100111 (
b01011010 .
11
#4240000
01
#4260000
b01101000 (
b01011011 .
11
#4280000
01
#4300000
b01101001 (
b01011100 .
11
#4320000
01
#4340000
b01101010 (
b01011101 .
11
#4360000
01
#4380000
b01101011 (
b01011110 .
11
#4400000
01
#4420000
b01101100 (
b01011111 .
11
#4440000
01
#4460000
b10 '
b00000000 (
b01100000 .
11
#4480000
01
#4500000
b00000001 (
b01100001 .
11
#4520000
01
#4540000
b00000010 (
b01100010 .
11
#4560000
01
#4580000
b00000011 (
b01100011 .
11
#4600000
01
#4620000
b00000100 (
b01100100 .
11
#4640000
01
#4660000
b00000101 (
b01100101 .
11
#4680000
01
#4700000
b00000110 (
b01100110 .
11
#4720000
01
#4740000
b00000111 (
b01100111 .
11
#4760000
01
#4780000
b00001000 (
b01101000 .
11
#4800000
01
#4820000
b00001001 (
b01101001 .
11
#4840000
01
#4860000
b00001010 (
b01101010 .
11
#4880000
01
#4900000
b00001011 (
b01101011 .
11
#4920000
01
#4940000
b00001100 (
b01101100 .
11
#4960000
01
#4980000
b00001101 (
b01101101 .
11
#5000000
01
#5020000
b00001110 (
b01101110 .
11
#5040000
01
#5060000
b00001111 (
b01101111 .
11
#5080000
01
#5100000
b00010000 (
b01110000 .
11
#5120000
01
#5140000
b00010001 (
b01110001 .
11
#5160000
01
#5180000
b00010010 (
b01110010 .
11
#5200000
01
#5220000
b00010011 (
b01110011 .
11
#5240000
01
#5260000
b00010100 (
b01110100 .
11
#5280000
01
#5300000
b00010101 (
b01110101 .
11
#5320000
01
#5340000
b00010110 (
b01110110 .
11
#5360000
01
#5380000
b00010111 (
b01110111 .
11
#5400000
01
#5420000
b00011000 (
b01111000 .
11
#5440000
01
#5460000
b00011001 (
b01111001 .
11
#5480000
01
#5500000
b00011010 (
b01111010 .
11
#5520000
01
#5540000
b00011011 (
b01111011 .
11
#5560000
01
#5580000
b00011100 (
b01111100 .
11
#5600000
01
#5620000
b00011101 (
b01111101 .
11
#5640000
01
#5660000
b00011110 (
b01111110 .
11
#5680000
01
#5700000
b00011111 (
b01111111 .
11
#5720000
01
#5740000
b00100000 (
b10000000 .
11
#5760000
01
#5780000
b00100001 (
b10000001 .
11
#5800000
01
#5820000
b00100010 (
b10000010 .
11
#5840000
01
#5860000
b00100011 (
b10000011 .
11
#5880000
01
#5900000
b00100100 (
b10000100 .
11
#5920000
01
#5940000
b00100101 (
b10000101 .
11
#5960000
01
#5980000
b00100110 (
b10000110 .
11
#6000000
01
#6020000
b00100111 (
b10000111 .
11
#6040000
01
#6060000
b00101000 (
b10001000 .
11
#6080000
01
#6100000
b00101001 (
b10001001 .
11
#6120000
01
#6140000
b00101010 (
b10001010 .
11
#6160000
01
#6180000
b00101011 (
b10001011 .
11
#6200000
01
#6220000
b00101100 (
b10001100 .
11
#6240000
01
#6260000
b00101101 (
b10001101 .
11
#6280000
01
#6300000
b00101110 (
b10001110 .
11
#6320000
01
#6340000
b00101111 (
b10001111 .
11
#6360000
01
#6380000
b00110000 (
b10010000 .
11
#6400000
01
#6420000
b00110001 (
b10010001 .
11
#6440000
01
#6460000
b00110010 (
b10010010 .
11
#6480000
01
#6500000
b00110011 (
b10010011 .
11
#6520000
01
#6540000
b00110100 (
b10010100 .
11
#6560000
01
#6580000
b00110101 (
b10010101 .
11
#6600000
01
#6620000
b00110110 (
b10010110 .
11
#6640000
01
#6660000
b00110111 (
b10010111 .
11
#6680000
01
#6700000
b00111000 (
b10011000 .
11
#6720000
01
#6740000
b00111001 (
b10011001 .
11
#6760000
01
#6780000
b00111010 (
b10011010 .
11
#6800000
01
#6820000
b00111011 (
b10011011 .
11
#6840000
01
#6860000
b00111100 (
b10011100 .
11
#6880000
01
#6900000
b00111101 (
b10011101 .
11
#6920000
01
#6940000
b00111110 (
b10011110 .
11
#6960000
01
#6980000
b00111111 (
b10011111 .
11
#7000000
01
#7020000
b01000000 (
b10100000 .
11
#7040000
01
#7060000
b01000001 (
b10100001 .
11
#7080000
01
#7100000
b01000010 (
b10100010 .
11
#7120000
01
#7140000
b01000011 (
b10100011 .
11
#7160000
01
#7180000
b01000100 (
b10100100 .
11
#7200000
01
#7220000
b01000101 (
b10100101 .
11
#7240000
01
#7260000
b01000110 (
b10100110 .
11
#7280000
01
#7300000
b01000111 (
b10100111 .
11
#7320000
01
#7340000
b01001000 (
b10101000 .
11
#7360000
01
#7380000
b01001001 (
b10101001 .
11
#7400000
01
#7420000
b01001010 (
b10101010 .
11
#7440000
01
#7460000
b01001011 (
b10101011 .
11
#7480000
01
#7500000
b01001100 (
b10101100 .
11
#7520000
01
#7540000
b01001101 (
b10101101 .
11
#7560000
01
#7580000
b01001110 (
b10101110 .
11
#7600000
01
#7620000
b01001111 (
b10101111 .
11
#7640000
01
#7660000
b01010000 (
b10110000 .
11
#7680000
01
#7700000
b01010001 (
b10110001 .
11
#7720000
01
#7740000
b01010010 (
b10110010 .
11
#7760000
01
#7780000
b01010011 (
b10110011 .
11
#7800000
01
#7820000
b01010100 (
b10110100 .
11
#7840000
01
#7860000
b01010101 (
b10110101 .
11
#7880000
01
#7900000
b01010110 (
b10110110 .
11
#7920000
01
#7940000
b01010111 (
b10110111 .
11
#7960000
01
#7980000
b01011000 (
b10111000 .
11
#8000000
01
#8020000
b01011001 (
b10111001 .
11
#8040000
01
#8060000
b01011010 (
b10111010 .
11
#8080000
01
#8100000
b01011011 (
b10111011 .
11
#8120000
01
#8140000
b01011100 (
b10111100 .
11
#8160000
01
#8180000
b01011101 (
b10111101 .
11
#8200000
01
#8220000
b01011110 (
b10111110 .
11
#8240000
01
#8260000
b01011111 (
b10111111 .
11
#8280000
01
#8300000
b01100000 (
b11000000 .
11
#8320000
01
#8340000
b01100001 (
b11000001 .
11
#8360000
01
#8380000
b01100010 (
b11000010 .
11
#8400000
01
#8420000
b01100011 (
b11000011 .
11
#8440000
01
#8460000
b01100100 (
b11000100 .
11
#8480000
01
#8500000
b01100101 (
b11000101 .
11
#8520000
01
#8540000
b01100110 (
b11000110 .
11
#8560000
01
#8580000
b01100111 (
b11000111 .
11
#8600000
01
#8620000
b01101000 (
b11001000 .
11
#8640000
01
#8660000
b01101001 (
b11001001 .
11
#8680000
01
#8700000
b01101010 (
b11001010 .
11
#8720000
01
#8740000
b01101011 (
b11001011 .
11
#8760000
01
#8780000
b01101100 (
b11001100 .
11
#8800000
01
#8820000
b01101101 (
b11001101 .
11
#8840000
01
#8860000
b01101110 (
b11001110 .
11
#8880000
01
#8900000
b01101111 (
b11001111 .
11
#8920000
01
#8940000
b01110000 (
b11010000 .
11
#8960000
01
#8980000
b01110001 (
b11010001 .
11
#9000000
01
#9020000
b01110010 (
b11010010 .
11
#9040000
01
#9060000
b01110011 (
b11010011 .
11
#9080000
01
#9100000
b01110100 (
b11010100 .
11
#9120000
01
#9140000
b01110101 (
b11010101 .
11
#9160000
01
#9180000
b01110110 (
b11010110 .
11
#9200000
01
#9220000
b01110111 (
b11010111 .
11
#9240000
01
#9260000
b01111000 (
b11011000 .
11
#9280000
01
#9300000
b01111001 (
b10 -
b00000000 .
11
#9320000
01
#9340000
b01111010 (
b00000001 .
11
#9360000
01
#9380000
b01111011 (
b00000010 .
11
#9400000
01
#9420000
b01111100 (
b00000011 .
11
#9440000
01
#9460000
b01111101 (
b00000100 .
11
#9480000
01
#9500000
b01111110 (
b00000101 .
11
#9520000
01
#9540000
b01111111 (
b00000110 .
11
#9560000
01
#9580000
b10000000 (
b00000111 .
11
#9600000
01
#9620000
b10000001 (
b00001000 .
11
#9640000
01
#9660000
b10000010 (
b00001001 .
11
#9680000
01
#9700000
b10000011 (
b00001010 .
11
#9720000
01
#9740000
b10000100 (
b00001011 .
11
#9760000
01
#9780000
b10000101 (
b00001100 .
11
#9800000
01
#9820000
b10000110 (
b00001101 .
11
#9840000
01
#9860000
b10000111 (
b00001110 .
11
#9880000
01
#9900000
b10001000 (
b00001111 .
11
#9920000
01
#9940000
b10001001 (
b00010000 .
11
#9960000
01
#9980000
b10001010 (
b00010001 .
11
#10000000
01
#10020000
b10001011 (
b00010010 .
11
#10040000
01
#10060000
b10001100 (
b00010011 .
11
#10080000
01
#10100000
b10001101 (
b00010100 .
11
#10120000
01
#10140000
b10001110 (
b00010101 .
11
#10160000
01
#10180000
b10001111 (
b00010110 .
11
#10200000
01
#10220000
b10010000 (
b00010111 .
11
#10240000
01
#10260000
b10010001 (
b00011000 .
11
#10280000
01
#10300000
b10010010 (
b00011001 .
11
#10320000
01
#10340000
b10010011 (
b00011010 .
11
#10360000
01
#10380000
b10010100 (
b00011011 .
11
#10400000
01
#10420000
b10010101 (
b00011100 .
11
#10440000
01
#10460000
b10010110 (
b00011101 .
11
#10480000
01
#10500000
b10010111 (
b00011110 .
11
#10520000
01
#10540000
b10011000 (
b00011111 .
11
#10560000
01
#10580000
b10011001 (
b00100000 .
11
#10600000
01
#10620000
b10011010 (
b00100001 .
11
#10640000
01
#10660000
b10011011 (
b00100010 .
11
#10680000
01
#10700000
b10011100 (
b00100011 .
11
#10720000
01
#10740000
b10011101 (
b00100100 .
11
#10760000
01
#10780000
b10011110 (
b00100101 .
11
#10800000
01
#10820000
b10011111 (
b00100110 .
11
#10840000
01
#10860000
b10100000 (
b00100111 .
11
#10880000
01
#10900000
b10100001 (
b00101000 .
11
#10920000
01
#10940000
b10100010 (
b00101001 .
11
#10960000
01
#10980000
b10100011 (
b00101010 .
11
#11000000
01
#11020000
b10100100 (
b00101011 .
11
#11040000
01
#11060000
b10100101 (
b00101100 .
11
#11080000
01
#11100000
b10100110 (
b00101101 .
11
#11120000
01
#11140000
b10100111 (
b00101110 .
11
#11160000
01
#11180000
b10101000 (
b00101111 .
11
#11200000
01
#11220000
b10101001 (
b00110000 .
11
#11240000
01
#11260000
b10101010 (
b00110001 .
11
#11280000
01
#11300000
b10101011 (
b00110010 .
11
#11320000
01
#11340000
b10101100 (
b00110011 .
11
#11360000
01
#11380000
b10101101 (
b00110100 .
11
#11400000
01
#11420000
b10101110 (
b00110101 .
11
#11440000
01
#11460000
b10101111 (
b00110110 .
11
#11480000
01
#11500000
b10110000 (
b00110111 .
11
#11520000
01
#11540000
b10110001 (
b00111000 .
11
#11560000
01
#11580000
b10110010 (
b00111001 .
11
#11600000
01
#11620000
b10110011 (
b00111010 .
11
#11640000
01
#11660000
b10110100 (
b00111011 .
11
#11680000
01
#11700000
b10110101 (
b00111100 .
11
#11720000
01
#11740000
b10110110 (
b00111101 .
11
#11760000
01
#11780000
b10110111 (
b00111110 .
11
#11800000
01
#11820000
b10111000 (
b00111111 .
11
#11840000
01
#11860000
b10111001 (
b01000000 .
11
#11880000
01
#11900000
b10111010 (
b01000001 .
11
#11920000
01
#11940000
b10111011 (
b01000010 .
11
#11960000
01
#11980000
b10111100 (
b01000011 .
11
#12000000
01
#12020000
b10111101 (
b01000100 .
11
#12040000
01
#12060000
b10111110 (
b01000101 .
11
#12080000
01
#12100000
b10111111 (
b01000110 .
11
#12120000
01
#12140000
b11000000 (
b01000111 .
11
#12160000
01
#12180000
b11000001 (
b01001000 .
11
#12200000
01
#12220000
b11000010 (
b01001001 .
11
#12240000
01
#12260000
b11000011 (
b01001010 .
11
#12280000
01
#12300000
b11000100 (
b01001011 .
11
#12320000
01
#12340000
b11000101 (
b01001100 .
11
#12360000
01
#12380000
b11000110 (
b01001101 .
11
#12400000
01
#12420000
b11000111 (
b01001110 .
11
#12440000
01
#12460000
b11001000 (
b01001111 .
11
#12480000
01
#12500000
b11001001 (
b01010000 .
11
#12520000
01
#12540000
b11001010 (
b01010001 .
11
#12560000
01
#12580000
b11001011 (
b01010010 .
11
#12600000
01
#12620000
b11001100 (
b01010011 .
11
#12640000
01
#12660000
b11001101 (
b01010100 .
11
#12680000
01
#12700000
b11001110 (
b01010101 .
11
#12720000
01
#12740000
b11001111 (
b01010110 .
11
#12760000
01
#12780000
b11010000 (
b01010111 .
11
#12800000
01
#12820000
b11010001 (
b01011000 .
11
#12840000
01
#12860000
b11010010 (
b01011001 .
11
#12880000
01
#12900000
b11010011 (
b01011010 .
11
#12920000
01
#12940000
b11010100 (
b01011011 .
11
#12960000
01
#12980000
b11010101 (
b01011100 .
11
#13000000
01
#13020000
b11010110 (
b01011101 .
11
#13040000
01
#13060000
b11010111 (
b01011110 .
11
#13080000
01
#13100000
b11011000 (
b01011111 .
11
#13120000
01
#13140000
b00000000 (
b001 )
b01100000 .
11
#13160000
01
#13180000
b00000001 (
b01100001 .
11
#13200000
01
#13220000
b00000010 (
b01100010 .
11
#13240000
01
#13260000
b00000011 (
b01100011 .
11
#13280000
01
#13300000
b00000100 (
b01100100 .
11
#13320000
01
#13340000
b00000101 (
b01100101 .
11
#13360000
01
#13380000
b00000110 (
b01100110 .
11
#13400000
01
#13420000
b00000111 (
b01100111 .
11
#13440000
01
#13460000
b00001000 (
b01101000 .
11
#13480000
01
#13500000
b00001001 (
b01101001 .
11
#13520000
01
#13540000
b00001010 (
b01101010 .
11
#13560000
01
#13580000
b00001011 (
b01101011 .
11
#13600000
01
#13620000
b00001100 (
b01101100 .
11
#13640000
01
#13660000
b00001101 (
b01101101 .
11
#13680000
01
#13700000
b00001110 (
b01101110 .
11
#13720000
01
#13740000
b00001111 (
b01101111 .
11
#13760000
01
#13780000
b00010000 (
b01110000 .
11
#13800000
01
#13820000
b00010001 (
b01110001 .
11
#13840000
01
#13860000
b00010010 (
b01110010 .
11
#13880000
01
#13900000
b00010011 (
b01110011 .
11
#13920000
01
#13940000
b00010100 (
b01110100 .
11
#13960000
01
#13980000
b00010101 (
b01110101 .
11
#14000000
01
#14020000
b00010110 (
b01110110 .
11
#14040000
01
#14060000
b00010111 (
b01110111 .
11
#14080000
01
#14100000
b00011000 (
b01111000 .
11
#14120000
01
#14140000
b00011001 (
b01111001 .
11
#14160000
01
#14180000
b00011010 (
b01111010 .
11
#14200000
01
#14220000
b00011011 (
b01111011 .
11
#14240000
01
#14260000
b00011100 (
b01111100 .
11
#14280000
01
#14300000
b00011101 (
b01111101 .
11
#14320000
01
#14340000
b00011110 (
b01111110 .
11
#14360000
01
#14380000
b00011111 (
b01111111 .
11
#14400000
01
#14420000
b00100000 (
b10000000 .
11
#14440000
01
#14460000
b00100001 (
b10000001 .
11
#14480000
01
#14500000
b00100010 (
b10000010 .
11
#14520000
01
#14540000
b00100011 (
b10000011 .
11
#14560000
01
#14580000
b00100100 (
b10000100 .
11
#14600000
01
#14620000
b00100101 (
b10000101 .
11
#14640000
01
#14660000
b00100110 (
b10000110 .
11
#14680000
01
#14700000
b00100111 (
b10000111 .
11
#14720000
01
#14740000
b00101000 (
b10001000 .
11
#14760000
01
#14780000
b00101001 (
b10001001 .
11
#14800000
01
#14820000
b00101010 (
b10001010 .
11
#14840000
01
#14860000
b00101011 (
b10001011 .
11
#14880000
01
#14900000
b00101100 (
b10001100 .
11
#14920000
01
#14940000
b00101101 (
b10001101 .
11
#14960000
01
#14980000
b00101110 (
b10001110 .
11
#15000000
01
#15020000
b00101111 (
b10001111 .
11
#15040000
01
#15060000
b00110000 (
b10010000 .
11
#15080000
01
#15100000
b00110001 (
b10010001 .
11
#15120000
01
#15140000
b00110010 (
b10010010 .
11
#15160000
01
#15180000
b00110011 (
b10010011 .
11
#15200000
01
#15220000
b00110100 (
b10010100 .
11
#15240000
01
#15260000
b00110101 (
b10010101 .
11
#15280000
01
#15300000
b00110110 (
b10010110 .
11
#15320000
01
#15340000
b00110111 (
b10010111 .
11
#15360000
01
#15380000
b00111000 (
b10011000 .
11
#15400000
01
#15420000
b00111001 (
b10011001 .
11
#15440000
01
#15460000
b00111010 (
b10011010 .
11
#15480000
01
#15500000
b00111011 (
b10011011 .
11
#15520000
01
#15540000
b00111100 (
b10011100 .
11
#15560000
01
#15580000
b00111101 (
b10011101 .
11
